[
  {
    "sample_id": "T14_1314_1318",
    "internal_id": 3990,
    "true_label": "教师巡视",
    "pred_label": "课堂沉寂",
    "true_idx": 3,
    "pred_idx": 9
  },
  {
    "sample_id": "T06_1905_1910",
    "internal_id": 934,
    "true_label": "教师巡视",
    "pred_label": "教师板书",
    "true_idx": 3,
    "pred_idx": 5
  },
  {
    "sample_id": "T04_1207_1211",
    "internal_id": 3210,
    "true_label": "教师巡视",
    "pred_label": "课堂沉寂",
    "true_idx": 3,
    "pred_idx": 9
  },
  {
    "sample_id": "T01_1519_1522",
    "internal_id": 1841,
    "true_label": "教师讲授",
    "pred_label": "学生发言",
    "true_idx": 2,
    "pred_idx": 1
  },
  {
    "sample_id": "T18_1437_1440",
    "internal_id": 219,
    "true_label": "教师巡视",
    "pred_label": "课堂沉寂",
    "true_idx": 3,
    "pred_idx": 9
  },
  {
    "sample_id": "T12_0367_0372",
    "internal_id": 3204,
    "true_label": "教师巡视",
    "pred_label": "课堂沉寂",
    "true_idx": 3,
    "pred_idx": 9
  },
  {
    "sample_id": "T17_2001_2006",
    "internal_id": 4004,
    "true_label": "教师巡视",
    "pred_label": "课堂沉寂",
    "true_idx": 3,
    "pred_idx": 9
  },
  {
    "sample_id": "T05_0991_0994",
    "internal_id": 4019,
    "true_label": "教师巡视",
    "pred_label": "课堂沉寂",
    "true_idx": 3,
    "pred_idx": 9
  },
  {
    "sample_id": "T19_2029_2034",
    "internal_id": 4267,
    "true_label": "教师巡视",
    "pred_label": "课堂沉寂",
    "true_idx": 3,
    "pred_idx": 9
  },
  {
    "sample_id": "T20_0778_0783",
    "internal_id": 920,
    "true_label": "教师板书",
    "pred_label": "教师巡视",
    "true_idx": 5,
    "pred_idx": 3
  },
  {
    "sample_id": "T13_0138_0141",
    "internal_id": 4147,
    "true_label": "教师板书",
    "pred_label": "教师巡视",
    "true_idx": 5,
    "pred_idx": 3
  },
  {
    "sample_id": "T17_1307_1311",
    "internal_id": 2012,
    "true_label": "课堂沉寂",
    "pred_label": "教师巡视",
    "true_idx": 9,
    "pred_idx": 3
  },
  {
    "sample_id": "T17_2294_2299",
    "internal_id": 4028,
    "true_label": "教师巡视",
    "pred_label": "教师板书",
    "true_idx": 3,
    "pred_idx": 5
  },
  {
    "sample_id": "T18_0118_0123",
    "internal_id": 2407,
    "true_label": "教师巡视",
    "pred_label": "课堂沉寂",
    "true_idx": 3,
    "pred_idx": 9
  },
  {
    "sample_id": "T15_1724_1727",
    "internal_id": 1764,
    "true_label": "教师巡视",
    "pred_label": "教师板书",
    "true_idx": 3,
    "pred_idx": 5
  },
  {
    "sample_id": "T04_1119_1123",
    "internal_id": 2437,
    "true_label": "教师巡视",
    "pred_label": "教师板书",
    "true_idx": 3,
    "pred_idx": 5
  },
  {
    "sample_id": "T09_1211_1216",
    "internal_id": 2486,
    "true_label": "教师巡视",
    "pred_label": "教师板书",
    "true_idx": 3,
    "pred_idx": 5
  },
  {
    "sample_id": "T32_1299_1303",
    "internal_id": 2579,
    "true_label": "教师巡视",
    "pred_label": "课堂沉寂",
    "true_idx": 3,
    "pred_idx": 9
  },
  {
    "sample_id": "T04_1245_1248",
    "internal_id": 2522,
    "true_label": "教师巡视",
    "pred_label": "课堂沉寂",
    "true_idx": 3,
    "pred_idx": 9
  },
  {
    "sample_id": "T16_2233_2237",
    "internal_id": 4061,
    "true_label": "教师巡视",
    "pred_label": "课堂沉寂",
    "true_idx": 3,
    "pred_idx": 9
  },
  {
    "sample_id": "T04_0564_0567",
    "internal_id": 3120,
    "true_label": "教师板书",
    "pred_label": "课堂沉寂",
    "true_idx": 5,
    "pred_idx": 9
  },
  {
    "sample_id": "T03_2245_2250",
    "internal_id": 1839,
    "true_label": "教师巡视",
    "pred_label": "课堂沉寂",
    "true_idx": 3,
    "pred_idx": 9
  },
  {
    "sample_id": "T03_2148_2152",
    "internal_id": 3419,
    "true_label": "教师巡视",
    "pred_label": "课堂沉寂",
    "true_idx": 3,
    "pred_idx": 9
  },
  {
    "sample_id": "T05_0601_0605",
    "internal_id": 3886,
    "true_label": "教师巡视",
    "pred_label": "课堂沉寂",
    "true_idx": 3,
    "pred_idx": 9
  },
  {
    "sample_id": "T02_1970_1973",
    "internal_id": 958,
    "true_label": "教师巡视",
    "pred_label": "课堂沉寂",
    "true_idx": 3,
    "pred_idx": 9
  },
  {
    "sample_id": "T12_0043_0046",
    "internal_id": 2443,
    "true_label": "教师板书",
    "pred_label": "课堂沉寂",
    "true_idx": 5,
    "pred_idx": 9
  },
  {
    "sample_id": "T11_0837_0840",
    "internal_id": 533,
    "true_label": "教师巡视",
    "pred_label": "课堂沉寂",
    "true_idx": 3,
    "pred_idx": 9
  },
  {
    "sample_id": "T30_2279_2282",
    "internal_id": 1664,
    "true_label": "教师巡视",
    "pred_label": "课堂沉寂",
    "true_idx": 3,
    "pred_idx": 9
  },
  {
    "sample_id": "T06_1880_1884",
    "internal_id": 1519,
    "true_label": "教师巡视",
    "pred_label": "课堂沉寂",
    "true_idx": 3,
    "pred_idx": 9
  },
  {
    "sample_id": "T16_1075_1079",
    "internal_id": 914,
    "true_label": "教师板书",
    "pred_label": "课堂沉寂",
    "true_idx": 5,
    "pred_idx": 9
  },
  {
    "sample_id": "T21_1184_1188",
    "internal_id": 1229,
    "true_label": "教师板书",
    "pred_label": "课堂沉寂",
    "true_idx": 5,
    "pred_idx": 9
  },
  {
    "sample_id": "T32_1746_1749",
    "internal_id": 1546,
    "true_label": "教师巡视",
    "pred_label": "课堂沉寂",
    "true_idx": 3,
    "pred_idx": 9
  },
  {
    "sample_id": "T05_0124_0129",
    "internal_id": 2053,
    "true_label": "教师板书",
    "pred_label": "课堂沉寂",
    "true_idx": 5,
    "pred_idx": 9
  },
  {
    "sample_id": "T13_0419_0422",
    "internal_id": 3111,
    "true_label": "教师巡视",
    "pred_label": "课堂沉寂",
    "true_idx": 3,
    "pred_idx": 9
  },
  {
    "sample_id": "T18_0551_0555",
    "internal_id": 2003,
    "true_label": "教师巡视",
    "pred_label": "课堂沉寂",
    "true_idx": 3,
    "pred_idx": 9
  },
  {
    "sample_id": "T20_1537_1541",
    "internal_id": 800,
    "true_label": "教师板书",
    "pred_label": "课堂沉寂",
    "true_idx": 5,
    "pred_idx": 9
  },
  {
    "sample_id": "T21_0938_0944",
    "internal_id": 2980,
    "true_label": "教师巡视",
    "pred_label": "课堂沉寂",
    "true_idx": 3,
    "pred_idx": 9
  },
  {
    "sample_id": "T07_1601_1605",
    "internal_id": 2822,
    "true_label": "教师板书",
    "pred_label": "课堂沉寂",
    "true_idx": 5,
    "pred_idx": 9
  },
  {
    "sample_id": "T16_1807_1811",
    "internal_id": 1673,
    "true_label": "教师板书",
    "pred_label": "课堂沉寂",
    "true_idx": 5,
    "pred_idx": 9
  },
  {
    "sample_id": "T18_1427_1430",
    "internal_id": 376,
    "true_label": "教师巡视",
    "pred_label": "课堂沉寂",
    "true_idx": 3,
    "pred_idx": 9
  },
  {
    "sample_id": "T21_1678_1682",
    "internal_id": 660,
    "true_label": "教师巡视",
    "pred_label": "课堂沉寂",
    "true_idx": 3,
    "pred_idx": 9
  },
  {
    "sample_id": "T06_0492_0495",
    "internal_id": 3319,
    "true_label": "教师巡视",
    "pred_label": "课堂沉寂",
    "true_idx": 3,
    "pred_idx": 9
  },
  {
    "sample_id": "T17_1361_1365",
    "internal_id": 2554,
    "true_label": "教师巡视",
    "pred_label": "课堂沉寂",
    "true_idx": 3,
    "pred_idx": 9
  },
  {
    "sample_id": "T03_2250_2256",
    "internal_id": 2250,
    "true_label": "教师巡视",
    "pred_label": "课堂沉寂",
    "true_idx": 3,
    "pred_idx": 9
  },
  {
    "sample_id": "T04_0290_0293",
    "internal_id": 2517,
    "true_label": "教师巡视",
    "pred_label": "课堂沉寂",
    "true_idx": 3,
    "pred_idx": 9
  },
  {
    "sample_id": "T03_2025_2031",
    "internal_id": 4275,
    "true_label": "教师巡视",
    "pred_label": "课堂沉寂",
    "true_idx": 3,
    "pred_idx": 9
  },
  {
    "sample_id": "T04_1722_1726",
    "internal_id": 2136,
    "true_label": "教师巡视",
    "pred_label": "课堂沉寂",
    "true_idx": 3,
    "pred_idx": 9
  },
  {
    "sample_id": "T10_1118_1122",
    "internal_id": 620,
    "true_label": "教师巡视",
    "pred_label": "课堂沉寂",
    "true_idx": 3,
    "pred_idx": 9
  },
  {
    "sample_id": "T16_2244_2247",
    "internal_id": 1109,
    "true_label": "教师巡视",
    "pred_label": "课堂沉寂",
    "true_idx": 3,
    "pred_idx": 9
  },
  {
    "sample_id": "T03_2115_2119",
    "internal_id": 154,
    "true_label": "教师巡视",
    "pred_label": "课堂沉寂",
    "true_idx": 3,
    "pred_idx": 9
  },
  {
    "sample_id": "T18_0469_0474",
    "internal_id": 1426,
    "true_label": "教师巡视",
    "pred_label": "课堂沉寂",
    "true_idx": 3,
    "pred_idx": 9
  },
  {
    "sample_id": "T21_0474_0479",
    "internal_id": 2118,
    "true_label": "教师巡视",
    "pred_label": "课堂沉寂",
    "true_idx": 3,
    "pred_idx": 9
  },
  {
    "sample_id": "T10_0468_0471",
    "internal_id": 3546,
    "true_label": "教师巡视",
    "pred_label": "课堂沉寂",
    "true_idx": 3,
    "pred_idx": 9
  },
  {
    "sample_id": "T05_2230_2235",
    "internal_id": 981,
    "true_label": "教师巡视",
    "pred_label": "课堂沉寂",
    "true_idx": 3,
    "pred_idx": 9
  },
  {
    "sample_id": "T32_1794_1797",
    "internal_id": 2807,
    "true_label": "教师巡视",
    "pred_label": "课堂沉寂",
    "true_idx": 3,
    "pred_idx": 9
  },
  {
    "sample_id": "T19_0351_0354",
    "internal_id": 2219,
    "true_label": "教师巡视",
    "pred_label": "课堂沉寂",
    "true_idx": 3,
    "pred_idx": 9
  },
  {
    "sample_id": "T03_1715_1719",
    "internal_id": 3235,
    "true_label": "教师巡视",
    "pred_label": "课堂沉寂",
    "true_idx": 3,
    "pred_idx": 9
  },
  {
    "sample_id": "T09_0877_0882",
    "internal_id": 2644,
    "true_label": "教师巡视",
    "pred_label": "课堂沉寂",
    "true_idx": 3,
    "pred_idx": 9
  },
  {
    "sample_id": "T09_0842_0846",
    "internal_id": 148,
    "true_label": "教师巡视",
    "pred_label": "课堂沉寂",
    "true_idx": 3,
    "pred_idx": 9
  },
  {
    "sample_id": "T13_0415_0419",
    "internal_id": 1643,
    "true_label": "教师巡视",
    "pred_label": "课堂沉寂",
    "true_idx": 3,
    "pred_idx": 9
  },
  {
    "sample_id": "T17_2282_2286",
    "internal_id": 122,
    "true_label": "教师巡视",
    "pred_label": "课堂沉寂",
    "true_idx": 3,
    "pred_idx": 9
  },
  {
    "sample_id": "T10_2063_2069",
    "internal_id": 233,
    "true_label": "教师巡视",
    "pred_label": "课堂沉寂",
    "true_idx": 3,
    "pred_idx": 9
  },
  {
    "sample_id": "T05_1661_1664",
    "internal_id": 3458,
    "true_label": "教师板书",
    "pred_label": "课堂沉寂",
    "true_idx": 5,
    "pred_idx": 9
  },
  {
    "sample_id": "T15_0062_0067",
    "internal_id": 1633,
    "true_label": "教师讲授",
    "pred_label": "学生发言",
    "true_idx": 2,
    "pred_idx": 1
  },
  {
    "sample_id": "T10_0386_0389",
    "internal_id": 1448,
    "true_label": "教师巡视",
    "pred_label": "课堂沉寂",
    "true_idx": 3,
    "pred_idx": 9
  },
  {
    "sample_id": "T08_0085_0090",
    "internal_id": 59,
    "true_label": "教师板书",
    "pred_label": "课堂沉寂",
    "true_idx": 5,
    "pred_idx": 9
  },
  {
    "sample_id": "T04_1378_1382",
    "internal_id": 719,
    "true_label": "教师讲授",
    "pred_label": "学生发言",
    "true_idx": 2,
    "pred_idx": 1
  },
  {
    "sample_id": "T08_0939_0943",
    "internal_id": 3527,
    "true_label": "教师巡视",
    "pred_label": "课堂沉寂",
    "true_idx": 3,
    "pred_idx": 9
  },
  {
    "sample_id": "T10_1135_1138",
    "internal_id": 2864,
    "true_label": "教师巡视",
    "pred_label": "课堂沉寂",
    "true_idx": 3,
    "pred_idx": 9
  },
  {
    "sample_id": "T17_2086_2090",
    "internal_id": 3962,
    "true_label": "教师巡视",
    "pred_label": "课堂沉寂",
    "true_idx": 3,
    "pred_idx": 9
  },
  {
    "sample_id": "T17_2299_2304",
    "internal_id": 4291,
    "true_label": "教师巡视",
    "pred_label": "课堂沉寂",
    "true_idx": 3,
    "pred_idx": 9
  },
  {
    "sample_id": "T32_1011_1016",
    "internal_id": 3794,
    "true_label": "教师巡视",
    "pred_label": "教师板书",
    "true_idx": 3,
    "pred_idx": 5
  },
  {
    "sample_id": "T21_1448_1453",
    "internal_id": 2593,
    "true_label": "教师巡视",
    "pred_label": "课堂沉寂",
    "true_idx": 3,
    "pred_idx": 9
  },
  {
    "sample_id": "T31_0495_0498",
    "internal_id": 3364,
    "true_label": "技术操作",
    "pred_label": "课堂沉寂",
    "true_idx": 7,
    "pred_idx": 9
  },
  {
    "sample_id": "T05_1027_1030",
    "internal_id": 2805,
    "true_label": "教师巡视",
    "pred_label": "课堂沉寂",
    "true_idx": 3,
    "pred_idx": 9
  },
  {
    "sample_id": "T10_1141_1144",
    "internal_id": 3551,
    "true_label": "教师巡视",
    "pred_label": "课堂沉寂",
    "true_idx": 3,
    "pred_idx": 9
  },
  {
    "sample_id": "T05_0313_0316",
    "internal_id": 634,
    "true_label": "教师板书",
    "pred_label": "课堂沉寂",
    "true_idx": 5,
    "pred_idx": 9
  },
  {
    "sample_id": "T04_1084_1087",
    "internal_id": 3742,
    "true_label": "教师巡视",
    "pred_label": "课堂沉寂",
    "true_idx": 3,
    "pred_idx": 9
  },
  {
    "sample_id": "T11_1240_1244",
    "internal_id": 3664,
    "true_label": "教师巡视",
    "pred_label": "课堂沉寂",
    "true_idx": 3,
    "pred_idx": 9
  },
  {
    "sample_id": "T04_0796_0800",
    "internal_id": 4363,
    "true_label": "教师巡视",
    "pred_label": "课堂沉寂",
    "true_idx": 3,
    "pred_idx": 9
  },
  {
    "sample_id": "T04_1116_1119",
    "internal_id": 1461,
    "true_label": "教师巡视",
    "pred_label": "课堂沉寂",
    "true_idx": 3,
    "pred_idx": 9
  },
  {
    "sample_id": "T05_0744_0747",
    "internal_id": 1785,
    "true_label": "教师巡视",
    "pred_label": "教师板书",
    "true_idx": 3,
    "pred_idx": 5
  },
  {
    "sample_id": "T04_1132_1136",
    "internal_id": 3335,
    "true_label": "教师巡视",
    "pred_label": "课堂沉寂",
    "true_idx": 3,
    "pred_idx": 9
  },
  {
    "sample_id": "T14_0274_0277",
    "internal_id": 1223,
    "true_label": "教师巡视",
    "pred_label": "课堂沉寂",
    "true_idx": 3,
    "pred_idx": 9
  },
  {
    "sample_id": "T11_1193_1197",
    "internal_id": 1937,
    "true_label": "教师巡视",
    "pred_label": "课堂沉寂",
    "true_idx": 3,
    "pred_idx": 9
  },
  {
    "sample_id": "T09_1670_1674",
    "internal_id": 1680,
    "true_label": "教师巡视",
    "pred_label": "课堂沉寂",
    "true_idx": 3,
    "pred_idx": 9
  },
  {
    "sample_id": "T12_0294_0297",
    "internal_id": 1253,
    "true_label": "教师巡视",
    "pred_label": "课堂沉寂",
    "true_idx": 3,
    "pred_idx": 9
  },
  {
    "sample_id": "T30_2294_2298",
    "internal_id": 3909,
    "true_label": "教师巡视",
    "pred_label": "技术操作",
    "true_idx": 3,
    "pred_idx": 7
  },
  {
    "sample_id": "T21_1650_1654",
    "internal_id": 1100,
    "true_label": "教师巡视",
    "pred_label": "教师板书",
    "true_idx": 3,
    "pred_idx": 5
  },
  {
    "sample_id": "T18_1477_1480",
    "internal_id": 854,
    "true_label": "教师巡视",
    "pred_label": "课堂沉寂",
    "true_idx": 3,
    "pred_idx": 9
  },
  {
    "sample_id": "T10_0461_0465",
    "internal_id": 3349,
    "true_label": "教师巡视",
    "pred_label": "课堂沉寂",
    "true_idx": 3,
    "pred_idx": 9
  },
  {
    "sample_id": "T04_1096_1100",
    "internal_id": 3928,
    "true_label": "教师巡视",
    "pred_label": "课堂沉寂",
    "true_idx": 3,
    "pred_idx": 9
  },
  {
    "sample_id": "T18_0109_0114",
    "internal_id": 2229,
    "true_label": "教师巡视",
    "pred_label": "课堂沉寂",
    "true_idx": 3,
    "pred_idx": 9
  },
  {
    "sample_id": "T09_0860_0865",
    "internal_id": 3019,
    "true_label": "教师巡视",
    "pred_label": "课堂沉寂",
    "true_idx": 3,
    "pred_idx": 9
  },
  {
    "sample_id": "T32_1783_1787",
    "internal_id": 950,
    "true_label": "教师巡视",
    "pred_label": "教师板书",
    "true_idx": 3,
    "pred_idx": 5
  },
  {
    "sample_id": "T30_1512_1517",
    "internal_id": 1480,
    "true_label": "教师巡视",
    "pred_label": "课堂沉寂",
    "true_idx": 3,
    "pred_idx": 9
  },
  {
    "sample_id": "T10_0486_0489",
    "internal_id": 4162,
    "true_label": "教师巡视",
    "pred_label": "课堂沉寂",
    "true_idx": 3,
    "pred_idx": 9
  },
  {
    "sample_id": "T03_1530_1533",
    "internal_id": 1377,
    "true_label": "教师巡视",
    "pred_label": "课堂沉寂",
    "true_idx": 3,
    "pred_idx": 9
  },
  {
    "sample_id": "T03_2181_2184",
    "internal_id": 662,
    "true_label": "教师巡视",
    "pred_label": "课堂沉寂",
    "true_idx": 3,
    "pred_idx": 9
  },
  {
    "sample_id": "T03_1719_1723",
    "internal_id": 1690,
    "true_label": "教师巡视",
    "pred_label": "课堂沉寂",
    "true_idx": 3,
    "pred_idx": 9
  },
  {
    "sample_id": "T18_1471_1474",
    "internal_id": 1748,
    "true_label": "教师巡视",
    "pred_label": "课堂沉寂",
    "true_idx": 3,
    "pred_idx": 9
  },
  {
    "sample_id": "T09_1713_1716",
    "internal_id": 3104,
    "true_label": "教师巡视",
    "pred_label": "课堂沉寂",
    "true_idx": 3,
    "pred_idx": 9
  },
  {
    "sample_id": "T16_2314_2317",
    "internal_id": 2256,
    "true_label": "教师巡视",
    "pred_label": "课堂沉寂",
    "true_idx": 3,
    "pred_idx": 9
  },
  {
    "sample_id": "T21_1936_1940",
    "internal_id": 2652,
    "true_label": "技术操作",
    "pred_label": "教师板书",
    "true_idx": 7,
    "pred_idx": 5
  },
  {
    "sample_id": "T13_0784_0789",
    "internal_id": 3944,
    "true_label": "教师巡视",
    "pred_label": "课堂沉寂",
    "true_idx": 3,
    "pred_idx": 9
  },
  {
    "sample_id": "T11_1897_1900",
    "internal_id": 151,
    "true_label": "教师讲授",
    "pred_label": "学生发言",
    "true_idx": 2,
    "pred_idx": 1
  },
  {
    "sample_id": "T18_0086_0091",
    "internal_id": 2821,
    "true_label": "教师巡视",
    "pred_label": "课堂沉寂",
    "true_idx": 3,
    "pred_idx": 9
  },
  {
    "sample_id": "T12_1709_1713",
    "internal_id": 3663,
    "true_label": "教师巡视",
    "pred_label": "课堂沉寂",
    "true_idx": 3,
    "pred_idx": 9
  },
  {
    "sample_id": "T32_1303_1306",
    "internal_id": 254,
    "true_label": "教师巡视",
    "pred_label": "课堂沉寂",
    "true_idx": 3,
    "pred_idx": 9
  },
  {
    "sample_id": "T01_1734_1738",
    "internal_id": 3340,
    "true_label": "教师巡视",
    "pred_label": "课堂沉寂",
    "true_idx": 3,
    "pred_idx": 9
  },
  {
    "sample_id": "T20_1802_1805",
    "internal_id": 2581,
    "true_label": "教师巡视",
    "pred_label": "教师板书",
    "true_idx": 3,
    "pred_idx": 5
  },
  {
    "sample_id": "T18_0100_0105",
    "internal_id": 4374,
    "true_label": "教师巡视",
    "pred_label": "课堂沉寂",
    "true_idx": 3,
    "pred_idx": 9
  },
  {
    "sample_id": "T32_2003_2007",
    "internal_id": 2705,
    "true_label": "教师巡视",
    "pred_label": "课堂沉寂",
    "true_idx": 3,
    "pred_idx": 9
  },
  {
    "sample_id": "T32_1321_1323",
    "internal_id": 2549,
    "true_label": "教师巡视",
    "pred_label": "课堂沉寂",
    "true_idx": 3,
    "pred_idx": 9
  },
  {
    "sample_id": "T18_1682_1686",
    "internal_id": 1182,
    "true_label": "教师讲授",
    "pred_label": "教师板书",
    "true_idx": 2,
    "pred_idx": 5
  },
  {
    "sample_id": "T18_1424_1427",
    "internal_id": 2287,
    "true_label": "教师巡视",
    "pred_label": "课堂沉寂",
    "true_idx": 3,
    "pred_idx": 9
  },
  {
    "sample_id": "T19_2015_2019",
    "internal_id": 3729,
    "true_label": "教师巡视",
    "pred_label": "课堂沉寂",
    "true_idx": 3,
    "pred_idx": 9
  },
  {
    "sample_id": "T04_1456_1460",
    "internal_id": 3205,
    "true_label": "教师巡视",
    "pred_label": "课堂沉寂",
    "true_idx": 3,
    "pred_idx": 9
  },
  {
    "sample_id": "T07_0940_0945",
    "internal_id": 363,
    "true_label": "教师巡视",
    "pred_label": "课堂沉寂",
    "true_idx": 3,
    "pred_idx": 9
  },
  {
    "sample_id": "T17_2090_2094",
    "internal_id": 3499,
    "true_label": "教师巡视",
    "pred_label": "课堂沉寂",
    "true_idx": 3,
    "pred_idx": 9
  },
  {
    "sample_id": "T17_2250_2253",
    "internal_id": 833,
    "true_label": "教师巡视",
    "pred_label": "课堂沉寂",
    "true_idx": 3,
    "pred_idx": 9
  },
  {
    "sample_id": "T12_0474_0478",
    "internal_id": 3650,
    "true_label": "教师巡视",
    "pred_label": "课堂沉寂",
    "true_idx": 3,
    "pred_idx": 9
  },
  {
    "sample_id": "T19_0360_0363",
    "internal_id": 659,
    "true_label": "教师巡视",
    "pred_label": "课堂沉寂",
    "true_idx": 3,
    "pred_idx": 9
  },
  {
    "sample_id": "T08_1573_1577",
    "internal_id": 3564,
    "true_label": "教师板书",
    "pred_label": "教师巡视",
    "true_idx": 5,
    "pred_idx": 3
  },
  {
    "sample_id": "T14_1629_1634",
    "internal_id": 3171,
    "true_label": "学生发言",
    "pred_label": "教师讲授",
    "true_idx": 1,
    "pred_idx": 2
  },
  {
    "sample_id": "T03_2192_2196",
    "internal_id": 2556,
    "true_label": "教师巡视",
    "pred_label": "课堂沉寂",
    "true_idx": 3,
    "pred_idx": 9
  },
  {
    "sample_id": "T19_2024_2029",
    "internal_id": 4264,
    "true_label": "教师巡视",
    "pred_label": "课堂沉寂",
    "true_idx": 3,
    "pred_idx": 9
  },
  {
    "sample_id": "T18_0077_0081",
    "internal_id": 1334,
    "true_label": "教师巡视",
    "pred_label": "课堂沉寂",
    "true_idx": 3,
    "pred_idx": 9
  },
  {
    "sample_id": "T04_0275_0278",
    "internal_id": 1554,
    "true_label": "教师巡视",
    "pred_label": "课堂沉寂",
    "true_idx": 3,
    "pred_idx": 9
  },
  {
    "sample_id": "T10_1722_1728",
    "internal_id": 298,
    "true_label": "教师巡视",
    "pred_label": "课堂沉寂",
    "true_idx": 3,
    "pred_idx": 9
  },
  {
    "sample_id": "T01_0644_0647",
    "internal_id": 3144,
    "true_label": "教师板书",
    "pred_label": "课堂沉寂",
    "true_idx": 5,
    "pred_idx": 9
  },
  {
    "sample_id": "T03_1619_1622",
    "internal_id": 3369,
    "true_label": "教师板书",
    "pred_label": "教师巡视",
    "true_idx": 5,
    "pred_idx": 3
  },
  {
    "sample_id": "T04_0735_0739",
    "internal_id": 1894,
    "true_label": "教师讲授",
    "pred_label": "学生发言",
    "true_idx": 2,
    "pred_idx": 1
  },
  {
    "sample_id": "T02_1897_1903",
    "internal_id": 50,
    "true_label": "教师巡视",
    "pred_label": "课堂沉寂",
    "true_idx": 3,
    "pred_idx": 9
  },
  {
    "sample_id": "T17_1333_1337",
    "internal_id": 2794,
    "true_label": "教师巡视",
    "pred_label": "课堂沉寂",
    "true_idx": 3,
    "pred_idx": 9
  },
  {
    "sample_id": "T11_1393_1398",
    "internal_id": 2265,
    "true_label": "教师巡视",
    "pred_label": "课堂沉寂",
    "true_idx": 3,
    "pred_idx": 9
  },
  {
    "sample_id": "T06_0374_0378",
    "internal_id": 3798,
    "true_label": "教师板书",
    "pred_label": "课堂沉寂",
    "true_idx": 5,
    "pred_idx": 9
  },
  {
    "sample_id": "T31_0772_0776",
    "internal_id": 2810,
    "true_label": "教师讲授",
    "pred_label": "学生发言",
    "true_idx": 2,
    "pred_idx": 1
  },
  {
    "sample_id": "T12_1844_1849",
    "internal_id": 3982,
    "true_label": "教师板书",
    "pred_label": "教师巡视",
    "true_idx": 5,
    "pred_idx": 3
  },
  {
    "sample_id": "T02_0998_1002",
    "internal_id": 1462,
    "true_label": "教师讲授",
    "pred_label": "学生发言",
    "true_idx": 2,
    "pred_idx": 1
  },
  {
    "sample_id": "T13_0703_0708",
    "internal_id": 1713,
    "true_label": "教师板书",
    "pred_label": "教师巡视",
    "true_idx": 5,
    "pred_idx": 3
  },
  {
    "sample_id": "T05_1703_1707",
    "internal_id": 2255,
    "true_label": "教师板书",
    "pred_label": "课堂沉寂",
    "true_idx": 5,
    "pred_idx": 9
  },
  {
    "sample_id": "T31_0835_0840",
    "internal_id": 565,
    "true_label": "教师巡视",
    "pred_label": "课堂沉寂",
    "true_idx": 3,
    "pred_idx": 9
  },
  {
    "sample_id": "T12_0134_0139",
    "internal_id": 3773,
    "true_label": "教师板书",
    "pred_label": "教师巡视",
    "true_idx": 5,
    "pred_idx": 3
  },
  {
    "sample_id": "T21_1376_1382",
    "internal_id": 722,
    "true_label": "教师巡视",
    "pred_label": "课堂沉寂",
    "true_idx": 3,
    "pred_idx": 9
  },
  {
    "sample_id": "T21_0221_0224",
    "internal_id": 1803,
    "true_label": "教师巡视",
    "pred_label": "教师板书",
    "true_idx": 3,
    "pred_idx": 5
  },
  {
    "sample_id": "T32_1804_1807",
    "internal_id": 386,
    "true_label": "教师巡视",
    "pred_label": "教师板书",
    "true_idx": 3,
    "pred_idx": 5
  },
  {
    "sample_id": "T19_2213_2219",
    "internal_id": 1107,
    "true_label": "教师反馈",
    "pred_label": "教师讲授",
    "true_idx": 6,
    "pred_idx": 2
  },
  {
    "sample_id": "T18_0524_0528",
    "internal_id": 544,
    "true_label": "教师巡视",
    "pred_label": "课堂沉寂",
    "true_idx": 3,
    "pred_idx": 9
  },
  {
    "sample_id": "T12_0333_0339",
    "internal_id": 715,
    "true_label": "教师巡视",
    "pred_label": "课堂沉寂",
    "true_idx": 3,
    "pred_idx": 9
  },
  {
    "sample_id": "T08_1695_1697",
    "internal_id": 3592,
    "true_label": "教师巡视",
    "pred_label": "教师板书",
    "true_idx": 3,
    "pred_idx": 5
  },
  {
    "sample_id": "T13_0781_0784",
    "internal_id": 518,
    "true_label": "教师巡视",
    "pred_label": "教师板书",
    "true_idx": 3,
    "pred_idx": 5
  },
  {
    "sample_id": "T05_0747_0751",
    "internal_id": 1187,
    "true_label": "教师巡视",
    "pred_label": "教师板书",
    "true_idx": 3,
    "pred_idx": 5
  },
  {
    "sample_id": "T05_0012_0015",
    "internal_id": 3743,
    "true_label": "技术操作",
    "pred_label": "教师板书",
    "true_idx": 7,
    "pred_idx": 5
  },
  {
    "sample_id": "T18_0095_0100",
    "internal_id": 4,
    "true_label": "教师巡视",
    "pred_label": "课堂沉寂",
    "true_idx": 3,
    "pred_idx": 9
  },
  {
    "sample_id": "T17_0489_0493",
    "internal_id": 2084,
    "true_label": "教师巡视",
    "pred_label": "课堂沉寂",
    "true_idx": 3,
    "pred_idx": 9
  },
  {
    "sample_id": "T18_2430_2434",
    "internal_id": 581,
    "true_label": "教师讲授",
    "pred_label": "学生发言",
    "true_idx": 2,
    "pred_idx": 1
  },
  {
    "sample_id": "T17_1314_1317",
    "internal_id": 2357,
    "true_label": "教师巡视",
    "pred_label": "课堂沉寂",
    "true_idx": 3,
    "pred_idx": 9
  },
  {
    "sample_id": "T32_0258_0261",
    "internal_id": 1416,
    "true_label": "教师讲授",
    "pred_label": "教师指令",
    "true_idx": 2,
    "pred_idx": 4
  },
  {
    "sample_id": "T19_2010_2015",
    "internal_id": 1194,
    "true_label": "教师巡视",
    "pred_label": "课堂沉寂",
    "true_idx": 3,
    "pred_idx": 9
  },
  {
    "sample_id": "T09_0080_0083",
    "internal_id": 2297,
    "true_label": "教师板书",
    "pred_label": "教师巡视",
    "true_idx": 5,
    "pred_idx": 3
  },
  {
    "sample_id": "T11_0650_0654",
    "internal_id": 429,
    "true_label": "教师讲授",
    "pred_label": "学生发言",
    "true_idx": 2,
    "pred_idx": 1
  },
  {
    "sample_id": "T16_1370_1374",
    "internal_id": 43,
    "true_label": "教师讲授",
    "pred_label": "学生发言",
    "true_idx": 2,
    "pred_idx": 1
  },
  {
    "sample_id": "T02_0971_0976",
    "internal_id": 4337,
    "true_label": "教师板书",
    "pred_label": "技术操作",
    "true_idx": 5,
    "pred_idx": 7
  },
  {
    "sample_id": "T13_1898_1902",
    "internal_id": 472,
    "true_label": "教师巡视",
    "pred_label": "课堂沉寂",
    "true_idx": 3,
    "pred_idx": 9
  },
  {
    "sample_id": "T18_1393_1396",
    "internal_id": 997,
    "true_label": "教师巡视",
    "pred_label": "课堂沉寂",
    "true_idx": 3,
    "pred_idx": 9
  },
  {
    "sample_id": "T03_1110_1115",
    "internal_id": 993,
    "true_label": "教师指令",
    "pred_label": "教师讲授",
    "true_idx": 4,
    "pred_idx": 2
  },
  {
    "sample_id": "T17_0544_0547",
    "internal_id": 3245,
    "true_label": "教师巡视",
    "pred_label": "课堂沉寂",
    "true_idx": 3,
    "pred_idx": 9
  },
  {
    "sample_id": "T15_1796_1802",
    "internal_id": 739,
    "true_label": "教师巡视",
    "pred_label": "课堂沉寂",
    "true_idx": 3,
    "pred_idx": 9
  },
  {
    "sample_id": "T08_1661_1664",
    "internal_id": 221,
    "true_label": "教师巡视",
    "pred_label": "课堂沉寂",
    "true_idx": 3,
    "pred_idx": 9
  },
  {
    "sample_id": "T10_0649_0652",
    "internal_id": 1320,
    "true_label": "教师巡视",
    "pred_label": "课堂沉寂",
    "true_idx": 3,
    "pred_idx": 9
  },
  {
    "sample_id": "T21_0642_0647",
    "internal_id": 2638,
    "true_label": "教师巡视",
    "pred_label": "课堂沉寂",
    "true_idx": 3,
    "pred_idx": 9
  },
  {
    "sample_id": "T15_1727_1731",
    "internal_id": 2077,
    "true_label": "教师巡视",
    "pred_label": "课堂沉寂",
    "true_idx": 3,
    "pred_idx": 9
  },
  {
    "sample_id": "T12_0532_0537",
    "internal_id": 2269,
    "true_label": "教师巡视",
    "pred_label": "课堂沉寂",
    "true_idx": 3,
    "pred_idx": 9
  },
  {
    "sample_id": "T04_0297_0301",
    "internal_id": 2616,
    "true_label": "教师巡视",
    "pred_label": "课堂沉寂",
    "true_idx": 3,
    "pred_idx": 9
  },
  {
    "sample_id": "T30_2135_2141",
    "internal_id": 3891,
    "true_label": "教师指令",
    "pred_label": "教师讲授",
    "true_idx": 4,
    "pred_idx": 2
  },
  {
    "sample_id": "T16_2251_2255",
    "internal_id": 469,
    "true_label": "教师巡视",
    "pred_label": "课堂沉寂",
    "true_idx": 3,
    "pred_idx": 9
  },
  {
    "sample_id": "T05_2260_2266",
    "internal_id": 1505,
    "true_label": "教师巡视",
    "pred_label": "课堂沉寂",
    "true_idx": 3,
    "pred_idx": 9
  },
  {
    "sample_id": "T18_0555_0559",
    "internal_id": 510,
    "true_label": "教师巡视",
    "pred_label": "课堂沉寂",
    "true_idx": 3,
    "pred_idx": 9
  },
  {
    "sample_id": "T16_1863_1867",
    "internal_id": 3176,
    "true_label": "教师指令",
    "pred_label": "教师讲授",
    "true_idx": 4,
    "pred_idx": 2
  },
  {
    "sample_id": "T16_1584_1589",
    "internal_id": 1528,
    "true_label": "学生发言",
    "pred_label": "教师讲授",
    "true_idx": 1,
    "pred_idx": 2
  },
  {
    "sample_id": "T05_0662_0665",
    "internal_id": 2263,
    "true_label": "教师巡视",
    "pred_label": "课堂沉寂",
    "true_idx": 3,
    "pred_idx": 9
  },
  {
    "sample_id": "T11_1552_1556",
    "internal_id": 2594,
    "true_label": "教师指令",
    "pred_label": "教师讲授",
    "true_idx": 4,
    "pred_idx": 2
  },
  {
    "sample_id": "T01_0164_0168",
    "internal_id": 1016,
    "true_label": "技术操作",
    "pred_label": "教师板书",
    "true_idx": 7,
    "pred_idx": 5
  },
  {
    "sample_id": "T13_0708_0714",
    "internal_id": 2553,
    "true_label": "教师板书",
    "pred_label": "教师巡视",
    "true_idx": 5,
    "pred_idx": 3
  },
  {
    "sample_id": "T06_1194_1198",
    "internal_id": 70,
    "true_label": "教师板书",
    "pred_label": "教师巡视",
    "true_idx": 5,
    "pred_idx": 3
  },
  {
    "sample_id": "T02_2292_2296",
    "internal_id": 3557,
    "true_label": "教师讲授",
    "pred_label": "学生发言",
    "true_idx": 2,
    "pred_idx": 1
  },
  {
    "sample_id": "T20_0102_0105",
    "internal_id": 2626,
    "true_label": "教师板书",
    "pred_label": "教师巡视",
    "true_idx": 5,
    "pred_idx": 3
  },
  {
    "sample_id": "T05_2077_2081",
    "internal_id": 689,
    "true_label": "教师板书",
    "pred_label": "教师巡视",
    "true_idx": 5,
    "pred_idx": 3
  },
  {
    "sample_id": "T17_1328_1333",
    "internal_id": 3618,
    "true_label": "教师巡视",
    "pred_label": "课堂沉寂",
    "true_idx": 3,
    "pred_idx": 9
  },
  {
    "sample_id": "T16_2269_2275",
    "internal_id": 3267,
    "true_label": "教师巡视",
    "pred_label": "课堂沉寂",
    "true_idx": 3,
    "pred_idx": 9
  },
  {
    "sample_id": "T18_1455_1458",
    "internal_id": 657,
    "true_label": "教师巡视",
    "pred_label": "课堂沉寂",
    "true_idx": 3,
    "pred_idx": 9
  },
  {
    "sample_id": "T21_2008_2011",
    "internal_id": 3130,
    "true_label": "教师讲授",
    "pred_label": "学生发言",
    "true_idx": 2,
    "pred_idx": 1
  },
  {
    "sample_id": "T06_0854_0858",
    "internal_id": 2952,
    "true_label": "教师巡视",
    "pred_label": "课堂沉寂",
    "true_idx": 3,
    "pred_idx": 9
  },
  {
    "sample_id": "T12_0438_0441",
    "internal_id": 2224,
    "true_label": "教师巡视",
    "pred_label": "教师板书",
    "true_idx": 3,
    "pred_idx": 5
  },
  {
    "sample_id": "T17_1408_1412",
    "internal_id": 2314,
    "true_label": "教师巡视",
    "pred_label": "课堂沉寂",
    "true_idx": 3,
    "pred_idx": 9
  },
  {
    "sample_id": "T18_0520_0524",
    "internal_id": 3504,
    "true_label": "教师巡视",
    "pred_label": "课堂沉寂",
    "true_idx": 3,
    "pred_idx": 9
  },
  {
    "sample_id": "T32_1293_1296",
    "internal_id": 2019,
    "true_label": "教师巡视",
    "pred_label": "课堂沉寂",
    "true_idx": 3,
    "pred_idx": 9
  },
  {
    "sample_id": "T14_1322_1326",
    "internal_id": 1864,
    "true_label": "教师巡视",
    "pred_label": "课堂沉寂",
    "true_idx": 3,
    "pred_idx": 9
  },
  {
    "sample_id": "T05_1698_1703",
    "internal_id": 761,
    "true_label": "教师板书",
    "pred_label": "课堂沉寂",
    "true_idx": 5,
    "pred_idx": 9
  },
  {
    "sample_id": "T14_0211_0214",
    "internal_id": 4368,
    "true_label": "教师板书",
    "pred_label": "教师巡视",
    "true_idx": 5,
    "pred_idx": 3
  },
  {
    "sample_id": "T31_0840_0844",
    "internal_id": 1751,
    "true_label": "教师巡视",
    "pred_label": "课堂沉寂",
    "true_idx": 3,
    "pred_idx": 9
  },
  {
    "sample_id": "T05_1030_1033",
    "internal_id": 47,
    "true_label": "教师巡视",
    "pred_label": "课堂沉寂",
    "true_idx": 3,
    "pred_idx": 9
  },
  {
    "sample_id": "T09_1784_1788",
    "internal_id": 2814,
    "true_label": "教师巡视",
    "pred_label": "课堂沉寂",
    "true_idx": 3,
    "pred_idx": 9
  },
  {
    "sample_id": "T05_1565_1570",
    "internal_id": 658,
    "true_label": "教师板书",
    "pred_label": "课堂沉寂",
    "true_idx": 5,
    "pred_idx": 9
  },
  {
    "sample_id": "T21_0613_0617",
    "internal_id": 1437,
    "true_label": "教师巡视",
    "pred_label": "教师板书",
    "true_idx": 3,
    "pred_idx": 5
  },
  {
    "sample_id": "T13_0526_0531",
    "internal_id": 2916,
    "true_label": "教师巡视",
    "pred_label": "课堂沉寂",
    "true_idx": 3,
    "pred_idx": 9
  },
  {
    "sample_id": "T18_0105_0109",
    "internal_id": 2239,
    "true_label": "教师巡视",
    "pred_label": "课堂沉寂",
    "true_idx": 3,
    "pred_idx": 9
  },
  {
    "sample_id": "T13_1308_1313",
    "internal_id": 2016,
    "true_label": "教师巡视",
    "pred_label": "课堂沉寂",
    "true_idx": 3,
    "pred_idx": 9
  },
  {
    "sample_id": "T08_0999_1005",
    "internal_id": 2045,
    "true_label": "教师巡视",
    "pred_label": "教师板书",
    "true_idx": 3,
    "pred_idx": 5
  },
  {
    "sample_id": "T09_1781_1784",
    "internal_id": 2675,
    "true_label": "教师巡视",
    "pred_label": "课堂沉寂",
    "true_idx": 3,
    "pred_idx": 9
  },
  {
    "sample_id": "T05_2073_2077",
    "internal_id": 683,
    "true_label": "教师板书",
    "pred_label": "教师巡视",
    "true_idx": 5,
    "pred_idx": 3
  },
  {
    "sample_id": "T17_2242_2246",
    "internal_id": 2661,
    "true_label": "教师巡视",
    "pred_label": "课堂沉寂",
    "true_idx": 3,
    "pred_idx": 9
  },
  {
    "sample_id": "T19_0354_0357",
    "internal_id": 1626,
    "true_label": "教师巡视",
    "pred_label": "课堂沉寂",
    "true_idx": 3,
    "pred_idx": 9
  },
  {
    "sample_id": "T10_1574_1577",
    "internal_id": 3433,
    "true_label": "学生发言",
    "pred_label": "教师提问",
    "true_idx": 1,
    "pred_idx": 0
  },
  {
    "sample_id": "T20_2278_2284",
    "internal_id": 3472,
    "true_label": "教师讲授",
    "pred_label": "教师反馈",
    "true_idx": 2,
    "pred_idx": 6
  },
  {
    "sample_id": "T19_0363_0366",
    "internal_id": 1595,
    "true_label": "教师巡视",
    "pred_label": "课堂沉寂",
    "true_idx": 3,
    "pred_idx": 9
  },
  {
    "sample_id": "T08_1316_1319",
    "internal_id": 3631,
    "true_label": "教师板书",
    "pred_label": "教师巡视",
    "true_idx": 5,
    "pred_idx": 3
  },
  {
    "sample_id": "T14_0305_0309",
    "internal_id": 395,
    "true_label": "教师反馈",
    "pred_label": "学生发言",
    "true_idx": 6,
    "pred_idx": 1
  },
  {
    "sample_id": "T32_1335_1339",
    "internal_id": 4085,
    "true_label": "教师巡视",
    "pred_label": "课堂沉寂",
    "true_idx": 3,
    "pred_idx": 9
  },
  {
    "sample_id": "T31_0444_0447",
    "internal_id": 1204,
    "true_label": "教师讲授",
    "pred_label": "学生发言",
    "true_idx": 2,
    "pred_idx": 1
  },
  {
    "sample_id": "T32_0199_0204",
    "internal_id": 4218,
    "true_label": "教师提问",
    "pred_label": "学生发言",
    "true_idx": 0,
    "pred_idx": 1
  },
  {
    "sample_id": "T18_0512_0516",
    "internal_id": 3422,
    "true_label": "教师巡视",
    "pred_label": "课堂沉寂",
    "true_idx": 3,
    "pred_idx": 9
  },
  {
    "sample_id": "T19_0366_0369",
    "internal_id": 249,
    "true_label": "教师巡视",
    "pred_label": "课堂沉寂",
    "true_idx": 3,
    "pred_idx": 9
  },
  {
    "sample_id": "T01_1936_1939",
    "internal_id": 1318,
    "true_label": "教师巡视",
    "pred_label": "课堂沉寂",
    "true_idx": 3,
    "pred_idx": 9
  },
  {
    "sample_id": "T17_1369_1372",
    "internal_id": 1184,
    "true_label": "教师板书",
    "pred_label": "教师巡视",
    "true_idx": 5,
    "pred_idx": 3
  },
  {
    "sample_id": "T03_1209_1213",
    "internal_id": 3366,
    "true_label": "教师巡视",
    "pred_label": "教师板书",
    "true_idx": 3,
    "pred_idx": 5
  },
  {
    "sample_id": "T32_1958_1961",
    "internal_id": 526,
    "true_label": "教师提问",
    "pred_label": "学生发言",
    "true_idx": 0,
    "pred_idx": 1
  },
  {
    "sample_id": "T19_0348_0351",
    "internal_id": 539,
    "true_label": "教师巡视",
    "pred_label": "课堂沉寂",
    "true_idx": 3,
    "pred_idx": 9
  },
  {
    "sample_id": "T09_1692_1698",
    "internal_id": 4032,
    "true_label": "教师巡视",
    "pred_label": "课堂沉寂",
    "true_idx": 3,
    "pred_idx": 9
  },
  {
    "sample_id": "T17_1372_1377",
    "internal_id": 1958,
    "true_label": "教师巡视",
    "pred_label": "课堂沉寂",
    "true_idx": 3,
    "pred_idx": 9
  },
  {
    "sample_id": "T17_1386_1391",
    "internal_id": 3420,
    "true_label": "教师巡视",
    "pred_label": "课堂沉寂",
    "true_idx": 3,
    "pred_idx": 9
  },
  {
    "sample_id": "T13_0155_0159",
    "internal_id": 119,
    "true_label": "教师板书",
    "pred_label": "教师巡视",
    "true_idx": 5,
    "pred_idx": 3
  },
  {
    "sample_id": "T17_0571_0574",
    "internal_id": 2853,
    "true_label": "教师巡视",
    "pred_label": "课堂沉寂",
    "true_idx": 3,
    "pred_idx": 9
  },
  {
    "sample_id": "T03_1533_1537",
    "internal_id": 929,
    "true_label": "教师巡视",
    "pred_label": "课堂沉寂",
    "true_idx": 3,
    "pred_idx": 9
  },
  {
    "sample_id": "T09_0424_0429",
    "internal_id": 3116,
    "true_label": "教师板书",
    "pred_label": "教师巡视",
    "true_idx": 5,
    "pred_idx": 3
  },
  {
    "sample_id": "T08_1319_1323",
    "internal_id": 1545,
    "true_label": "教师板书",
    "pred_label": "教师巡视",
    "true_idx": 5,
    "pred_idx": 3
  },
  {
    "sample_id": "T09_1097_1103",
    "internal_id": 2563,
    "true_label": "教师板书",
    "pred_label": "课堂沉寂",
    "true_idx": 5,
    "pred_idx": 9
  },
  {
    "sample_id": "T04_1412_1416",
    "internal_id": 1745,
    "true_label": "教师反馈",
    "pred_label": "教师讲授",
    "true_idx": 6,
    "pred_idx": 2
  },
  {
    "sample_id": "T21_1188_1193",
    "internal_id": 131,
    "true_label": "教师板书",
    "pred_label": "教师巡视",
    "true_idx": 5,
    "pred_idx": 3
  },
  {
    "sample_id": "T09_1791_1794",
    "internal_id": 2285,
    "true_label": "教师巡视",
    "pred_label": "课堂沉寂",
    "true_idx": 3,
    "pred_idx": 9
  },
  {
    "sample_id": "T18_2073_2076",
    "internal_id": 2318,
    "true_label": "教师讲授",
    "pred_label": "教师板书",
    "true_idx": 2,
    "pred_idx": 5
  },
  {
    "sample_id": "T04_0472_0477",
    "internal_id": 700,
    "true_label": "教师板书",
    "pred_label": "课堂沉寂",
    "true_idx": 5,
    "pred_idx": 9
  },
  {
    "sample_id": "T04_0324_0329",
    "internal_id": 1708,
    "true_label": "教师巡视",
    "pred_label": "课堂沉寂",
    "true_idx": 3,
    "pred_idx": 9
  },
  {
    "sample_id": "T12_1328_1331",
    "internal_id": 100,
    "true_label": "教师巡视",
    "pred_label": "课堂沉寂",
    "true_idx": 3,
    "pred_idx": 9
  },
  {
    "sample_id": "T18_1412_1415",
    "internal_id": 2212,
    "true_label": "教师巡视",
    "pred_label": "课堂沉寂",
    "true_idx": 3,
    "pred_idx": 9
  },
  {
    "sample_id": "T05_0700_0704",
    "internal_id": 2680,
    "true_label": "教师巡视",
    "pred_label": "课堂沉寂",
    "true_idx": 3,
    "pred_idx": 9
  },
  {
    "sample_id": "T01_1738_1742",
    "internal_id": 1433,
    "true_label": "教师巡视",
    "pred_label": "教师板书",
    "true_idx": 3,
    "pred_idx": 5
  },
  {
    "sample_id": "T12_1697_1702",
    "internal_id": 2547,
    "true_label": "教师巡视",
    "pred_label": "教师板书",
    "true_idx": 3,
    "pred_idx": 5
  },
  {
    "sample_id": "T16_0241_0244",
    "internal_id": 1148,
    "true_label": "教师巡视",
    "pred_label": "教师讲授",
    "true_idx": 3,
    "pred_idx": 2
  },
  {
    "sample_id": "T11_1347_1352",
    "internal_id": 1934,
    "true_label": "教师巡视",
    "pred_label": "课堂沉寂",
    "true_idx": 3,
    "pred_idx": 9
  },
  {
    "sample_id": "T14_0044_0047",
    "internal_id": 2112,
    "true_label": "教师反馈",
    "pred_label": "学生发言",
    "true_idx": 6,
    "pred_idx": 1
  },
  {
    "sample_id": "T18_1491_1495",
    "internal_id": 1826,
    "true_label": "教师巡视",
    "pred_label": "教师板书",
    "true_idx": 3,
    "pred_idx": 5
  },
  {
    "sample_id": "T12_0061_0063",
    "internal_id": 3764,
    "true_label": "技术操作",
    "pred_label": "教师板书",
    "true_idx": 7,
    "pred_idx": 5
  },
  {
    "sample_id": "T05_0015_0018",
    "internal_id": 4346,
    "true_label": "技术操作",
    "pred_label": "教师板书",
    "true_idx": 7,
    "pred_idx": 5
  },
  {
    "sample_id": "T19_0864_0870",
    "internal_id": 282,
    "true_label": "课堂沉寂",
    "pred_label": "教师巡视",
    "true_idx": 9,
    "pred_idx": 3
  },
  {
    "sample_id": "T01_0811_0816",
    "internal_id": 1991,
    "true_label": "教师巡视",
    "pred_label": "课堂沉寂",
    "true_idx": 3,
    "pred_idx": 9
  },
  {
    "sample_id": "T05_0704_0707",
    "internal_id": 2291,
    "true_label": "教师巡视",
    "pred_label": "课堂沉寂",
    "true_idx": 3,
    "pred_idx": 9
  },
  {
    "sample_id": "T16_1193_1196",
    "internal_id": 68,
    "true_label": "教师巡视",
    "pred_label": "技术操作",
    "true_idx": 3,
    "pred_idx": 7
  },
  {
    "sample_id": "T16_1131_1135",
    "internal_id": 2312,
    "true_label": "教师巡视",
    "pred_label": "技术操作",
    "true_idx": 3,
    "pred_idx": 7
  },
  {
    "sample_id": "T02_0483_0488",
    "internal_id": 3427,
    "true_label": "教师巡视",
    "pred_label": "课堂沉寂",
    "true_idx": 3,
    "pred_idx": 9
  },
  {
    "sample_id": "T17_0507_0512",
    "internal_id": 3161,
    "true_label": "教师巡视",
    "pred_label": "课堂沉寂",
    "true_idx": 3,
    "pred_idx": 9
  },
  {
    "sample_id": "T17_2253_2257",
    "internal_id": 3146,
    "true_label": "教师巡视",
    "pred_label": "课堂沉寂",
    "true_idx": 3,
    "pred_idx": 9
  },
  {
    "sample_id": "T09_0839_0842",
    "internal_id": 4186,
    "true_label": "教师巡视",
    "pred_label": "教师板书",
    "true_idx": 3,
    "pred_idx": 5
  },
  {
    "sample_id": "T09_0882_0886",
    "internal_id": 1411,
    "true_label": "教师巡视",
    "pred_label": "技术操作",
    "true_idx": 3,
    "pred_idx": 7
  },
  {
    "sample_id": "T01_1816_1820",
    "internal_id": 4255,
    "true_label": "教师巡视",
    "pred_label": "课堂沉寂",
    "true_idx": 3,
    "pred_idx": 9
  },
  {
    "sample_id": "T21_0585_0588",
    "internal_id": 2251,
    "true_label": "教师板书",
    "pred_label": "教师巡视",
    "true_idx": 5,
    "pred_idx": 3
  },
  {
    "sample_id": "T14_1295_1298",
    "internal_id": 1867,
    "true_label": "教师巡视",
    "pred_label": "课堂沉寂",
    "true_idx": 3,
    "pred_idx": 9
  },
  {
    "sample_id": "T12_0478_0482",
    "internal_id": 1522,
    "true_label": "教师巡视",
    "pred_label": "课堂沉寂",
    "true_idx": 3,
    "pred_idx": 9
  },
  {
    "sample_id": "T09_1788_1791",
    "internal_id": 2882,
    "true_label": "教师巡视",
    "pred_label": "课堂沉寂",
    "true_idx": 3,
    "pred_idx": 9
  },
  {
    "sample_id": "T05_0299_0303",
    "internal_id": 892,
    "true_label": "教师板书",
    "pred_label": "技术操作",
    "true_idx": 5,
    "pred_idx": 7
  },
  {
    "sample_id": "T12_0053_0058",
    "internal_id": 3583,
    "true_label": "教师板书",
    "pred_label": "技术操作",
    "true_idx": 5,
    "pred_idx": 7
  },
  {
    "sample_id": "T19_2184_2189",
    "internal_id": 3961,
    "true_label": "教师板书",
    "pred_label": "技术操作",
    "true_idx": 5,
    "pred_idx": 7
  },
  {
    "sample_id": "T21_2342_2345",
    "internal_id": 2898,
    "true_label": "教师板书",
    "pred_label": "教师巡视",
    "true_idx": 5,
    "pred_idx": 3
  },
  {
    "sample_id": "T13_0800_0805",
    "internal_id": 3725,
    "true_label": "教师巡视",
    "pred_label": "课堂沉寂",
    "true_idx": 3,
    "pred_idx": 9
  },
  {
    "sample_id": "T13_1278_1283",
    "internal_id": 4184,
    "true_label": "教师巡视",
    "pred_label": "课堂沉寂",
    "true_idx": 3,
    "pred_idx": 9
  },
  {
    "sample_id": "T10_0658_0661",
    "internal_id": 3283,
    "true_label": "课堂沉寂",
    "pred_label": "教师巡视",
    "true_idx": 9,
    "pred_idx": 3
  }
]