[
  {
    "sample_id": "T09_1670_1674",
    "internal_id": 1680,
    "true_label": "教师巡视",
    "pred_label": "课堂沉寂",
    "true_idx": 3,
    "pred_idx": 9
  },
  {
    "sample_id": "T01_1816_1820",
    "internal_id": 4255,
    "true_label": "教师巡视",
    "pred_label": "课堂沉寂",
    "true_idx": 3,
    "pred_idx": 9
  },
  {
    "sample_id": "T06_0498_0503",
    "internal_id": 1660,
    "true_label": "教师巡视",
    "pred_label": "教师板书",
    "true_idx": 3,
    "pred_idx": 5
  },
  {
    "sample_id": "T18_0547_0551",
    "internal_id": 3137,
    "true_label": "教师巡视",
    "pred_label": "课堂沉寂",
    "true_idx": 3,
    "pred_idx": 9
  },
  {
    "sample_id": "T10_1722_1728",
    "internal_id": 298,
    "true_label": "教师巡视",
    "pred_label": "课堂沉寂",
    "true_idx": 3,
    "pred_idx": 9
  },
  {
    "sample_id": "T31_0844_0848",
    "internal_id": 1711,
    "true_label": "教师巡视",
    "pred_label": "学生发言",
    "true_idx": 3,
    "pred_idx": 1
  },
  {
    "sample_id": "T16_0635_0639",
    "internal_id": 3389,
    "true_label": "教师巡视",
    "pred_label": "课堂沉寂",
    "true_idx": 3,
    "pred_idx": 9
  },
  {
    "sample_id": "T16_1592_1596",
    "internal_id": 192,
    "true_label": "教师板书",
    "pred_label": "课堂沉寂",
    "true_idx": 5,
    "pred_idx": 9
  },
  {
    "sample_id": "T20_1784_1788",
    "internal_id": 3977,
    "true_label": "教师巡视",
    "pred_label": "课堂沉寂",
    "true_idx": 3,
    "pred_idx": 9
  },
  {
    "sample_id": "T06_1178_1182",
    "internal_id": 2217,
    "true_label": "教师板书",
    "pred_label": "课堂沉寂",
    "true_idx": 5,
    "pred_idx": 9
  },
  {
    "sample_id": "T32_1746_1749",
    "internal_id": 1546,
    "true_label": "教师巡视",
    "pred_label": "课堂沉寂",
    "true_idx": 3,
    "pred_idx": 9
  },
  {
    "sample_id": "T05_1027_1030",
    "internal_id": 2805,
    "true_label": "教师巡视",
    "pred_label": "课堂沉寂",
    "true_idx": 3,
    "pred_idx": 9
  },
  {
    "sample_id": "T04_0939_0945",
    "internal_id": 652,
    "true_label": "教师巡视",
    "pred_label": "课堂沉寂",
    "true_idx": 3,
    "pred_idx": 9
  },
  {
    "sample_id": "T12_0333_0339",
    "internal_id": 715,
    "true_label": "教师巡视",
    "pred_label": "课堂沉寂",
    "true_idx": 3,
    "pred_idx": 9
  },
  {
    "sample_id": "T18_1477_1480",
    "internal_id": 854,
    "true_label": "教师巡视",
    "pred_label": "课堂沉寂",
    "true_idx": 3,
    "pred_idx": 9
  },
  {
    "sample_id": "T12_0134_0139",
    "internal_id": 3773,
    "true_label": "教师板书",
    "pred_label": "课堂沉寂",
    "true_idx": 5,
    "pred_idx": 9
  },
  {
    "sample_id": "T10_1766_1770",
    "internal_id": 199,
    "true_label": "教师巡视",
    "pred_label": "课堂沉寂",
    "true_idx": 3,
    "pred_idx": 9
  },
  {
    "sample_id": "T18_0416_0420",
    "internal_id": 4228,
    "true_label": "教师板书",
    "pred_label": "课堂沉寂",
    "true_idx": 5,
    "pred_idx": 9
  },
  {
    "sample_id": "T15_1605_1610",
    "internal_id": 1271,
    "true_label": "教师板书",
    "pred_label": "课堂沉寂",
    "true_idx": 5,
    "pred_idx": 9
  },
  {
    "sample_id": "T19_2015_2019",
    "internal_id": 3729,
    "true_label": "教师巡视",
    "pred_label": "课堂沉寂",
    "true_idx": 3,
    "pred_idx": 9
  },
  {
    "sample_id": "T03_2266_2270",
    "internal_id": 3854,
    "true_label": "教师巡视",
    "pred_label": "课堂沉寂",
    "true_idx": 3,
    "pred_idx": 9
  },
  {
    "sample_id": "T04_0314_0319",
    "internal_id": 449,
    "true_label": "教师巡视",
    "pred_label": "课堂沉寂",
    "true_idx": 3,
    "pred_idx": 9
  },
  {
    "sample_id": "T05_1661_1664",
    "internal_id": 3458,
    "true_label": "教师板书",
    "pred_label": "课堂沉寂",
    "true_idx": 5,
    "pred_idx": 9
  },
  {
    "sample_id": "T05_0313_0316",
    "internal_id": 634,
    "true_label": "教师板书",
    "pred_label": "课堂沉寂",
    "true_idx": 5,
    "pred_idx": 9
  },
  {
    "sample_id": "T16_0241_0244",
    "internal_id": 1148,
    "true_label": "教师巡视",
    "pred_label": "课堂沉寂",
    "true_idx": 3,
    "pred_idx": 9
  },
  {
    "sample_id": "T16_0745_0748",
    "internal_id": 2049,
    "true_label": "教师巡视",
    "pred_label": "课堂沉寂",
    "true_idx": 3,
    "pred_idx": 9
  },
  {
    "sample_id": "T16_0095_0099",
    "internal_id": 1255,
    "true_label": "学生发言",
    "pred_label": "课堂沉寂",
    "true_idx": 1,
    "pred_idx": 9
  },
  {
    "sample_id": "T13_1308_1313",
    "internal_id": 2016,
    "true_label": "教师巡视",
    "pred_label": "课堂沉寂",
    "true_idx": 3,
    "pred_idx": 9
  },
  {
    "sample_id": "T02_1545_1548",
    "internal_id": 3923,
    "true_label": "教师板书",
    "pred_label": "课堂沉寂",
    "true_idx": 5,
    "pred_idx": 9
  },
  {
    "sample_id": "T14_0735_0739",
    "internal_id": 902,
    "true_label": "教师板书",
    "pred_label": "课堂沉寂",
    "true_idx": 5,
    "pred_idx": 9
  },
  {
    "sample_id": "T32_0178_0182",
    "internal_id": 537,
    "true_label": "教师讲授",
    "pred_label": "课堂沉寂",
    "true_idx": 2,
    "pred_idx": 9
  },
  {
    "sample_id": "T20_0108_0111",
    "internal_id": 1518,
    "true_label": "技术操作",
    "pred_label": "课堂沉寂",
    "true_idx": 7,
    "pred_idx": 9
  },
  {
    "sample_id": "T12_1328_1331",
    "internal_id": 100,
    "true_label": "教师巡视",
    "pred_label": "课堂沉寂",
    "true_idx": 3,
    "pred_idx": 9
  },
  {
    "sample_id": "T11_0455_0458",
    "internal_id": 1893,
    "true_label": "教师讲授",
    "pred_label": "学生发言",
    "true_idx": 2,
    "pred_idx": 1
  },
  {
    "sample_id": "T04_1903_1908",
    "internal_id": 2934,
    "true_label": "教师讲授",
    "pred_label": "学生发言",
    "true_idx": 2,
    "pred_idx": 1
  },
  {
    "sample_id": "T12_1709_1713",
    "internal_id": 3663,
    "true_label": "教师巡视",
    "pred_label": "课堂沉寂",
    "true_idx": 3,
    "pred_idx": 9
  },
  {
    "sample_id": "T12_0771_0774",
    "internal_id": 346,
    "true_label": "教师反馈",
    "pred_label": "学生发言",
    "true_idx": 6,
    "pred_idx": 1
  },
  {
    "sample_id": "T05_0401_0406",
    "internal_id": 872,
    "true_label": "教师板书",
    "pred_label": "课堂沉寂",
    "true_idx": 5,
    "pred_idx": 9
  },
  {
    "sample_id": "T16_2327_2331",
    "internal_id": 799,
    "true_label": "教师巡视",
    "pred_label": "课堂沉寂",
    "true_idx": 3,
    "pred_idx": 9
  },
  {
    "sample_id": "T19_1475_1478",
    "internal_id": 1797,
    "true_label": "教师板书",
    "pred_label": "课堂沉寂",
    "true_idx": 5,
    "pred_idx": 9
  },
  {
    "sample_id": "T18_0524_0528",
    "internal_id": 544,
    "true_label": "教师巡视",
    "pred_label": "课堂沉寂",
    "true_idx": 3,
    "pred_idx": 9
  },
  {
    "sample_id": "T13_0740_0743",
    "internal_id": 191,
    "true_label": "教师板书",
    "pred_label": "课堂沉寂",
    "true_idx": 5,
    "pred_idx": 9
  },
  {
    "sample_id": "T10_0486_0489",
    "internal_id": 4162,
    "true_label": "教师巡视",
    "pred_label": "课堂沉寂",
    "true_idx": 3,
    "pred_idx": 9
  },
  {
    "sample_id": "T08_0686_0691",
    "internal_id": 2110,
    "true_label": "教师板书",
    "pred_label": "课堂沉寂",
    "true_idx": 5,
    "pred_idx": 9
  },
  {
    "sample_id": "T17_1828_1832",
    "internal_id": 3469,
    "true_label": "教师讲授",
    "pred_label": "学生发言",
    "true_idx": 2,
    "pred_idx": 1
  },
  {
    "sample_id": "T02_2382_2387",
    "internal_id": 3100,
    "true_label": "教师反馈",
    "pred_label": "教师讲授",
    "true_idx": 6,
    "pred_idx": 2
  },
  {
    "sample_id": "T01_2391_2396",
    "internal_id": 371,
    "true_label": "教师讲授",
    "pred_label": "学生发言",
    "true_idx": 2,
    "pred_idx": 1
  },
  {
    "sample_id": "T15_1071_1075",
    "internal_id": 3009,
    "true_label": "教师指令",
    "pred_label": "教师讲授",
    "true_idx": 4,
    "pred_idx": 2
  },
  {
    "sample_id": "T16_1460_1464",
    "internal_id": 1147,
    "true_label": "教师指令",
    "pred_label": "教师讲授",
    "true_idx": 4,
    "pred_idx": 2
  },
  {
    "sample_id": "T10_2292_2296",
    "internal_id": 439,
    "true_label": "教师提问",
    "pred_label": "学生发言",
    "true_idx": 0,
    "pred_idx": 1
  },
  {
    "sample_id": "T07_1265_1270",
    "internal_id": 3728,
    "true_label": "教师巡视",
    "pred_label": "课堂沉寂",
    "true_idx": 3,
    "pred_idx": 9
  },
  {
    "sample_id": "T09_0121_0124",
    "internal_id": 1508,
    "true_label": "教师指令",
    "pred_label": "教师讲授",
    "true_idx": 4,
    "pred_idx": 2
  },
  {
    "sample_id": "T17_0091_0095",
    "internal_id": 2540,
    "true_label": "教师板书",
    "pred_label": "课堂沉寂",
    "true_idx": 5,
    "pred_idx": 9
  },
  {
    "sample_id": "T17_2282_2286",
    "internal_id": 122,
    "true_label": "教师巡视",
    "pred_label": "课堂沉寂",
    "true_idx": 3,
    "pred_idx": 9
  },
  {
    "sample_id": "T31_1072_1077",
    "internal_id": 2926,
    "true_label": "教师讲授",
    "pred_label": "学生发言",
    "true_idx": 2,
    "pred_idx": 1
  },
  {
    "sample_id": "T04_1100_1103",
    "internal_id": 3183,
    "true_label": "教师巡视",
    "pred_label": "课堂沉寂",
    "true_idx": 3,
    "pred_idx": 9
  },
  {
    "sample_id": "T03_2078_2081",
    "internal_id": 2641,
    "true_label": "教师巡视",
    "pred_label": "课堂沉寂",
    "true_idx": 3,
    "pred_idx": 9
  },
  {
    "sample_id": "T02_2154_2159",
    "internal_id": 603,
    "true_label": "教师提问",
    "pred_label": "教师讲授",
    "true_idx": 0,
    "pred_idx": 2
  },
  {
    "sample_id": "T07_0035_0038",
    "internal_id": 3391,
    "true_label": "教师板书",
    "pred_label": "教师讲授",
    "true_idx": 5,
    "pred_idx": 2
  },
  {
    "sample_id": "T03_1106_1110",
    "internal_id": 2448,
    "true_label": "教师提问",
    "pred_label": "学生发言",
    "true_idx": 0,
    "pred_idx": 1
  },
  {
    "sample_id": "T10_0729_0733",
    "internal_id": 3122,
    "true_label": "教师巡视",
    "pred_label": "教师讲授",
    "true_idx": 3,
    "pred_idx": 2
  },
  {
    "sample_id": "T06_1880_1884",
    "internal_id": 1519,
    "true_label": "教师巡视",
    "pred_label": "课堂沉寂",
    "true_idx": 3,
    "pred_idx": 9
  },
  {
    "sample_id": "T32_1944_1947",
    "internal_id": 1513,
    "true_label": "教师反馈",
    "pred_label": "课堂沉寂",
    "true_idx": 6,
    "pred_idx": 9
  },
  {
    "sample_id": "T21_1376_1382",
    "internal_id": 722,
    "true_label": "教师巡视",
    "pred_label": "学生发言",
    "true_idx": 3,
    "pred_idx": 1
  },
  {
    "sample_id": "T20_1124_1128",
    "internal_id": 3514,
    "true_label": "教师指令",
    "pred_label": "教师讲授",
    "true_idx": 4,
    "pred_idx": 2
  },
  {
    "sample_id": "T05_1703_1707",
    "internal_id": 2255,
    "true_label": "教师板书",
    "pred_label": "教师讲授",
    "true_idx": 5,
    "pred_idx": 2
  },
  {
    "sample_id": "T18_0105_0109",
    "internal_id": 2239,
    "true_label": "教师巡视",
    "pred_label": "课堂沉寂",
    "true_idx": 3,
    "pred_idx": 9
  },
  {
    "sample_id": "T20_0152_0156",
    "internal_id": 462,
    "true_label": "教师板书",
    "pred_label": "教师讲授",
    "true_idx": 5,
    "pred_idx": 2
  },
  {
    "sample_id": "T09_0860_0865",
    "internal_id": 3019,
    "true_label": "教师巡视",
    "pred_label": "课堂沉寂",
    "true_idx": 3,
    "pred_idx": 9
  },
  {
    "sample_id": "T08_1573_1577",
    "internal_id": 3564,
    "true_label": "教师板书",
    "pred_label": "课堂沉寂",
    "true_idx": 5,
    "pred_idx": 9
  },
  {
    "sample_id": "T01_1519_1522",
    "internal_id": 1841,
    "true_label": "教师讲授",
    "pred_label": "学生发言",
    "true_idx": 2,
    "pred_idx": 1
  },
  {
    "sample_id": "T17_2440_2443",
    "internal_id": 2198,
    "true_label": "教师指令",
    "pred_label": "教师讲授",
    "true_idx": 4,
    "pred_idx": 2
  },
  {
    "sample_id": "T19_1618_1621",
    "internal_id": 227,
    "true_label": "教师讲授",
    "pred_label": "学生发言",
    "true_idx": 2,
    "pred_idx": 1
  },
  {
    "sample_id": "T21_0628_0632",
    "internal_id": 2748,
    "true_label": "教师巡视",
    "pred_label": "课堂沉寂",
    "true_idx": 3,
    "pred_idx": 9
  },
  {
    "sample_id": "T01_1936_1939",
    "internal_id": 1318,
    "true_label": "教师巡视",
    "pred_label": "课堂沉寂",
    "true_idx": 3,
    "pred_idx": 9
  },
  {
    "sample_id": "T09_1784_1788",
    "internal_id": 2814,
    "true_label": "教师巡视",
    "pred_label": "课堂沉寂",
    "true_idx": 3,
    "pred_idx": 9
  },
  {
    "sample_id": "T06_1963_1967",
    "internal_id": 1303,
    "true_label": "学生发言",
    "pred_label": "教师讲授",
    "true_idx": 1,
    "pred_idx": 2
  },
  {
    "sample_id": "T20_2155_2159",
    "internal_id": 2673,
    "true_label": "教师讲授",
    "pred_label": "教师提问",
    "true_idx": 2,
    "pred_idx": 0
  },
  {
    "sample_id": "T18_1484_1487",
    "internal_id": 3036,
    "true_label": "教师巡视",
    "pred_label": "课堂沉寂",
    "true_idx": 3,
    "pred_idx": 9
  },
  {
    "sample_id": "T18_0392_0395",
    "internal_id": 2238,
    "true_label": "教师板书",
    "pred_label": "教师讲授",
    "true_idx": 5,
    "pred_idx": 2
  },
  {
    "sample_id": "T05_0672_0676",
    "internal_id": 2315,
    "true_label": "教师巡视",
    "pred_label": "教师讲授",
    "true_idx": 3,
    "pred_idx": 2
  },
  {
    "sample_id": "T15_0043_0047",
    "internal_id": 394,
    "true_label": "教师讲授",
    "pred_label": "课堂沉寂",
    "true_idx": 2,
    "pred_idx": 9
  },
  {
    "sample_id": "T18_0235_0239",
    "internal_id": 3681,
    "true_label": "教师指令",
    "pred_label": "课堂沉寂",
    "true_idx": 4,
    "pred_idx": 9
  },
  {
    "sample_id": "T10_1763_1766",
    "internal_id": 4412,
    "true_label": "教师巡视",
    "pred_label": "课堂沉寂",
    "true_idx": 3,
    "pred_idx": 9
  },
  {
    "sample_id": "T01_0186_0190",
    "internal_id": 2373,
    "true_label": "教师提问",
    "pred_label": "课堂沉寂",
    "true_idx": 0,
    "pred_idx": 9
  },
  {
    "sample_id": "T14_0319_0322",
    "internal_id": 3035,
    "true_label": "学生发言",
    "pred_label": "课堂沉寂",
    "true_idx": 1,
    "pred_idx": 9
  },
  {
    "sample_id": "T18_2463_2466",
    "internal_id": 2576,
    "true_label": "学生发言",
    "pred_label": "课堂沉寂",
    "true_idx": 1,
    "pred_idx": 9
  },
  {
    "sample_id": "T15_2173_2177",
    "internal_id": 3938,
    "true_label": "学生发言",
    "pred_label": "课堂沉寂",
    "true_idx": 1,
    "pred_idx": 9
  },
  {
    "sample_id": "T10_0741_0744",
    "internal_id": 723,
    "true_label": "教师指令",
    "pred_label": "课堂沉寂",
    "true_idx": 4,
    "pred_idx": 9
  },
  {
    "sample_id": "T10_1554_1557",
    "internal_id": 2543,
    "true_label": "学生发言",
    "pred_label": "课堂沉寂",
    "true_idx": 1,
    "pred_idx": 9
  },
  {
    "sample_id": "T06_1950_1955",
    "internal_id": 839,
    "true_label": "学生发言",
    "pred_label": "教师讲授",
    "true_idx": 1,
    "pred_idx": 2
  },
  {
    "sample_id": "T20_1856_1859",
    "internal_id": 4347,
    "true_label": "教师巡视",
    "pred_label": "课堂沉寂",
    "true_idx": 3,
    "pred_idx": 9
  },
  {
    "sample_id": "T17_2001_2006",
    "internal_id": 4004,
    "true_label": "教师巡视",
    "pred_label": "课堂沉寂",
    "true_idx": 3,
    "pred_idx": 9
  },
  {
    "sample_id": "T02_2224_2229",
    "internal_id": 2859,
    "true_label": "教师讲授",
    "pred_label": "教师提问",
    "true_idx": 2,
    "pred_idx": 0
  },
  {
    "sample_id": "T13_0708_0714",
    "internal_id": 2553,
    "true_label": "教师板书",
    "pred_label": "课堂沉寂",
    "true_idx": 5,
    "pred_idx": 9
  },
  {
    "sample_id": "T17_1333_1337",
    "internal_id": 2794,
    "true_label": "教师巡视",
    "pred_label": "课堂沉寂",
    "true_idx": 3,
    "pred_idx": 9
  },
  {
    "sample_id": "T17_1029_1035",
    "internal_id": 3490,
    "true_label": "教师讲授",
    "pred_label": "学生发言",
    "true_idx": 2,
    "pred_idx": 1
  },
  {
    "sample_id": "T21_0490_0495",
    "internal_id": 2264,
    "true_label": "教师巡视",
    "pred_label": "课堂沉寂",
    "true_idx": 3,
    "pred_idx": 9
  },
  {
    "sample_id": "T12_0107_0110",
    "internal_id": 1668,
    "true_label": "教师讲授",
    "pred_label": "学生发言",
    "true_idx": 2,
    "pred_idx": 1
  },
  {
    "sample_id": "T12_0550_0554",
    "internal_id": 2535,
    "true_label": "教师讲授",
    "pred_label": "学生发言",
    "true_idx": 2,
    "pred_idx": 1
  },
  {
    "sample_id": "T17_2086_2090",
    "internal_id": 3962,
    "true_label": "教师巡视",
    "pred_label": "课堂沉寂",
    "true_idx": 3,
    "pred_idx": 9
  },
  {
    "sample_id": "T19_0584_0587",
    "internal_id": 592,
    "true_label": "教师板书",
    "pred_label": "课堂沉寂",
    "true_idx": 5,
    "pred_idx": 9
  },
  {
    "sample_id": "T31_1058_1063",
    "internal_id": 1221,
    "true_label": "教师讲授",
    "pred_label": "学生发言",
    "true_idx": 2,
    "pred_idx": 1
  },
  {
    "sample_id": "T08_1306_1309",
    "internal_id": 1339,
    "true_label": "教师指令",
    "pred_label": "教师讲授",
    "true_idx": 4,
    "pred_idx": 2
  },
  {
    "sample_id": "T10_0645_0649",
    "internal_id": 803,
    "true_label": "教师巡视",
    "pred_label": "课堂沉寂",
    "true_idx": 3,
    "pred_idx": 9
  },
  {
    "sample_id": "T10_1320_1324",
    "internal_id": 507,
    "true_label": "教师巡视",
    "pred_label": "课堂沉寂",
    "true_idx": 3,
    "pred_idx": 9
  },
  {
    "sample_id": "T04_1315_1319",
    "internal_id": 2899,
    "true_label": "教师巡视",
    "pred_label": "课堂沉寂",
    "true_idx": 3,
    "pred_idx": 9
  },
  {
    "sample_id": "T21_0545_0550",
    "internal_id": 1549,
    "true_label": "教师板书",
    "pred_label": "课堂沉寂",
    "true_idx": 5,
    "pred_idx": 9
  },
  {
    "sample_id": "T04_1144_1147",
    "internal_id": 2523,
    "true_label": "教师巡视",
    "pred_label": "课堂沉寂",
    "true_idx": 3,
    "pred_idx": 9
  },
  {
    "sample_id": "T16_1101_1104",
    "internal_id": 2519,
    "true_label": "教师巡视",
    "pred_label": "学生发言",
    "true_idx": 3,
    "pred_idx": 1
  },
  {
    "sample_id": "T14_1021_1025",
    "internal_id": 1191,
    "true_label": "教师反馈",
    "pred_label": "教师讲授",
    "true_idx": 6,
    "pred_idx": 2
  },
  {
    "sample_id": "T11_1513_1516",
    "internal_id": 1966,
    "true_label": "教师巡视",
    "pred_label": "课堂沉寂",
    "true_idx": 3,
    "pred_idx": 9
  },
  {
    "sample_id": "T33_0903_0908",
    "internal_id": 1978,
    "true_label": "教师巡视",
    "pred_label": "课堂沉寂",
    "true_idx": 3,
    "pred_idx": 9
  },
  {
    "sample_id": "T21_0320_0324",
    "internal_id": 244,
    "true_label": "教师巡视",
    "pred_label": "课堂沉寂",
    "true_idx": 3,
    "pred_idx": 9
  },
  {
    "sample_id": "T19_2024_2029",
    "internal_id": 4264,
    "true_label": "教师巡视",
    "pred_label": "课堂沉寂",
    "true_idx": 3,
    "pred_idx": 9
  },
  {
    "sample_id": "T16_0603_0606",
    "internal_id": 3544,
    "true_label": "教师提问",
    "pred_label": "教师讲授",
    "true_idx": 0,
    "pred_idx": 2
  },
  {
    "sample_id": "T09_0489_0492",
    "internal_id": 639,
    "true_label": "学生讨论",
    "pred_label": "学生发言",
    "true_idx": 8,
    "pred_idx": 1
  },
  {
    "sample_id": "T19_2323_2326",
    "internal_id": 2323,
    "true_label": "教师指令",
    "pred_label": "教师讲授",
    "true_idx": 4,
    "pred_idx": 2
  },
  {
    "sample_id": "T21_0103_0108",
    "internal_id": 2537,
    "true_label": "教师板书",
    "pred_label": "教师讲授",
    "true_idx": 5,
    "pred_idx": 2
  },
  {
    "sample_id": "T19_0348_0351",
    "internal_id": 539,
    "true_label": "教师巡视",
    "pred_label": "课堂沉寂",
    "true_idx": 3,
    "pred_idx": 9
  },
  {
    "sample_id": "T13_1267_1273",
    "internal_id": 1063,
    "true_label": "教师巡视",
    "pred_label": "课堂沉寂",
    "true_idx": 3,
    "pred_idx": 9
  },
  {
    "sample_id": "T05_0676_0679",
    "internal_id": 3314,
    "true_label": "教师巡视",
    "pred_label": "学生发言",
    "true_idx": 3,
    "pred_idx": 1
  },
  {
    "sample_id": "T21_0885_0889",
    "internal_id": 2220,
    "true_label": "教师巡视",
    "pred_label": "课堂沉寂",
    "true_idx": 3,
    "pred_idx": 9
  },
  {
    "sample_id": "T17_2021_2024",
    "internal_id": 2471,
    "true_label": "教师板书",
    "pred_label": "课堂沉寂",
    "true_idx": 5,
    "pred_idx": 9
  },
  {
    "sample_id": "T03_1530_1533",
    "internal_id": 1377,
    "true_label": "教师巡视",
    "pred_label": "课堂沉寂",
    "true_idx": 3,
    "pred_idx": 9
  },
  {
    "sample_id": "T19_0948_0953",
    "internal_id": 3194,
    "true_label": "教师指令",
    "pred_label": "教师讲授",
    "true_idx": 4,
    "pred_idx": 2
  },
  {
    "sample_id": "T21_2591_2596",
    "internal_id": 3014,
    "true_label": "教师指令",
    "pred_label": "教师讲授",
    "true_idx": 4,
    "pred_idx": 2
  },
  {
    "sample_id": "T11_2326_2330",
    "internal_id": 3926,
    "true_label": "教师指令",
    "pred_label": "教师讲授",
    "true_idx": 4,
    "pred_idx": 2
  },
  {
    "sample_id": "T32_1775_1780",
    "internal_id": 3218,
    "true_label": "教师巡视",
    "pred_label": "课堂沉寂",
    "true_idx": 3,
    "pred_idx": 9
  },
  {
    "sample_id": "T09_1489_1492",
    "internal_id": 3192,
    "true_label": "教师指令",
    "pred_label": "教师讲授",
    "true_idx": 4,
    "pred_idx": 2
  },
  {
    "sample_id": "T09_1781_1784",
    "internal_id": 2675,
    "true_label": "教师巡视",
    "pred_label": "课堂沉寂",
    "true_idx": 3,
    "pred_idx": 9
  },
  {
    "sample_id": "T04_1084_1087",
    "internal_id": 3742,
    "true_label": "教师巡视",
    "pred_label": "课堂沉寂",
    "true_idx": 3,
    "pred_idx": 9
  },
  {
    "sample_id": "T18_0555_0559",
    "internal_id": 510,
    "true_label": "教师巡视",
    "pred_label": "课堂沉寂",
    "true_idx": 3,
    "pred_idx": 9
  },
  {
    "sample_id": "T01_0735_0738",
    "internal_id": 31,
    "true_label": "教师板书",
    "pred_label": "课堂沉寂",
    "true_idx": 5,
    "pred_idx": 9
  },
  {
    "sample_id": "T14_0044_0047",
    "internal_id": 2112,
    "true_label": "教师反馈",
    "pred_label": "学生发言",
    "true_idx": 6,
    "pred_idx": 1
  },
  {
    "sample_id": "T15_2059_2063",
    "internal_id": 1578,
    "true_label": "教师指令",
    "pred_label": "教师讲授",
    "true_idx": 4,
    "pred_idx": 2
  },
  {
    "sample_id": "T32_0492_0498",
    "internal_id": 2056,
    "true_label": "教师讲授",
    "pred_label": "学生发言",
    "true_idx": 2,
    "pred_idx": 1
  },
  {
    "sample_id": "T19_1526_1528",
    "internal_id": 3094,
    "true_label": "教师指令",
    "pred_label": "教师讲授",
    "true_idx": 4,
    "pred_idx": 2
  },
  {
    "sample_id": "T09_1304_1307",
    "internal_id": 198,
    "true_label": "教师指令",
    "pred_label": "教师讲授",
    "true_idx": 4,
    "pred_idx": 2
  },
  {
    "sample_id": "T02_1093_1099",
    "internal_id": 1968,
    "true_label": "教师板书",
    "pred_label": "课堂沉寂",
    "true_idx": 5,
    "pred_idx": 9
  },
  {
    "sample_id": "T13_0767_0772",
    "internal_id": 2483,
    "true_label": "教师板书",
    "pred_label": "课堂沉寂",
    "true_idx": 5,
    "pred_idx": 9
  },
  {
    "sample_id": "T06_1186_1190",
    "internal_id": 1922,
    "true_label": "教师板书",
    "pred_label": "教师巡视",
    "true_idx": 5,
    "pred_idx": 3
  },
  {
    "sample_id": "T08_0551_0555",
    "internal_id": 3755,
    "true_label": "教师板书",
    "pred_label": "课堂沉寂",
    "true_idx": 5,
    "pred_idx": 9
  },
  {
    "sample_id": "T30_2179_2184",
    "internal_id": 2713,
    "true_label": "教师巡视",
    "pred_label": "课堂沉寂",
    "true_idx": 3,
    "pred_idx": 9
  },
  {
    "sample_id": "T16_0626_0629",
    "internal_id": 4369,
    "true_label": "教师巡视",
    "pred_label": "教师提问",
    "true_idx": 3,
    "pred_idx": 0
  },
  {
    "sample_id": "T07_0045_0048",
    "internal_id": 3987,
    "true_label": "教师板书",
    "pred_label": "课堂沉寂",
    "true_idx": 5,
    "pred_idx": 9
  },
  {
    "sample_id": "T04_0361_0367",
    "internal_id": 764,
    "true_label": "教师板书",
    "pred_label": "课堂沉寂",
    "true_idx": 5,
    "pred_idx": 9
  },
  {
    "sample_id": "T17_2027_2030",
    "internal_id": 3610,
    "true_label": "教师板书",
    "pred_label": "课堂沉寂",
    "true_idx": 5,
    "pred_idx": 9
  },
  {
    "sample_id": "T31_1186_1190",
    "internal_id": 704,
    "true_label": "教师讲授",
    "pred_label": "学生发言",
    "true_idx": 2,
    "pred_idx": 1
  },
  {
    "sample_id": "T10_0312_0316",
    "internal_id": 3416,
    "true_label": "教师板书",
    "pred_label": "课堂沉寂",
    "true_idx": 5,
    "pred_idx": 9
  },
  {
    "sample_id": "T19_1337_1341",
    "internal_id": 21,
    "true_label": "技术操作",
    "pred_label": "教师讲授",
    "true_idx": 7,
    "pred_idx": 2
  },
  {
    "sample_id": "T10_0193_0196",
    "internal_id": 3186,
    "true_label": "教师讲授",
    "pred_label": "教师指令",
    "true_idx": 2,
    "pred_idx": 4
  },
  {
    "sample_id": "T31_0551_0554",
    "internal_id": 4382,
    "true_label": "技术操作",
    "pred_label": "教师指令",
    "true_idx": 7,
    "pred_idx": 4
  },
  {
    "sample_id": "T02_1033_1039",
    "internal_id": 1405,
    "true_label": "学生发言",
    "pred_label": "教师讲授",
    "true_idx": 1,
    "pred_idx": 2
  },
  {
    "sample_id": "T16_1176_1181",
    "internal_id": 3018,
    "true_label": "教师巡视",
    "pred_label": "学生发言",
    "true_idx": 3,
    "pred_idx": 1
  },
  {
    "sample_id": "T20_1667_1671",
    "internal_id": 960,
    "true_label": "教师讲授",
    "pred_label": "教师指令",
    "true_idx": 2,
    "pred_idx": 4
  },
  {
    "sample_id": "T30_2241_2246",
    "internal_id": 262,
    "true_label": "学生讨论",
    "pred_label": "学生发言",
    "true_idx": 8,
    "pred_idx": 1
  },
  {
    "sample_id": "T21_1555_1559",
    "internal_id": 3066,
    "true_label": "教师反馈",
    "pred_label": "教师讲授",
    "true_idx": 6,
    "pred_idx": 2
  },
  {
    "sample_id": "T30_0182_0186",
    "internal_id": 52,
    "true_label": "学生讨论",
    "pred_label": "学生发言",
    "true_idx": 8,
    "pred_idx": 1
  },
  {
    "sample_id": "T21_2271_2274",
    "internal_id": 4295,
    "true_label": "教师板书",
    "pred_label": "教师提问",
    "true_idx": 5,
    "pred_idx": 0
  },
  {
    "sample_id": "T32_1303_1306",
    "internal_id": 254,
    "true_label": "教师巡视",
    "pred_label": "课堂沉寂",
    "true_idx": 3,
    "pred_idx": 9
  },
  {
    "sample_id": "T16_1167_1172",
    "internal_id": 1378,
    "true_label": "教师巡视",
    "pred_label": "教师讲授",
    "true_idx": 3,
    "pred_idx": 2
  },
  {
    "sample_id": "T06_1905_1910",
    "internal_id": 934,
    "true_label": "教师巡视",
    "pred_label": "课堂沉寂",
    "true_idx": 3,
    "pred_idx": 9
  },
  {
    "sample_id": "T19_1329_1332",
    "internal_id": 1073,
    "true_label": "技术操作",
    "pred_label": "教师讲授",
    "true_idx": 7,
    "pred_idx": 2
  },
  {
    "sample_id": "T16_1429_1434",
    "internal_id": 2429,
    "true_label": "教师指令",
    "pred_label": "教师板书",
    "true_idx": 4,
    "pred_idx": 5
  },
  {
    "sample_id": "T04_0472_0477",
    "internal_id": 700,
    "true_label": "教师板书",
    "pred_label": "课堂沉寂",
    "true_idx": 5,
    "pred_idx": 9
  },
  {
    "sample_id": "T01_0528_0532",
    "internal_id": 2190,
    "true_label": "教师提问",
    "pred_label": "教师板书",
    "true_idx": 0,
    "pred_idx": 5
  },
  {
    "sample_id": "T32_1797_1800",
    "internal_id": 1688,
    "true_label": "教师巡视",
    "pred_label": "课堂沉寂",
    "true_idx": 3,
    "pred_idx": 9
  },
  {
    "sample_id": "T02_1103_1107",
    "internal_id": 777,
    "true_label": "教师板书",
    "pred_label": "课堂沉寂",
    "true_idx": 5,
    "pred_idx": 9
  },
  {
    "sample_id": "T04_0351_0356",
    "internal_id": 2657,
    "true_label": "教师板书",
    "pred_label": "课堂沉寂",
    "true_idx": 5,
    "pred_idx": 9
  },
  {
    "sample_id": "T32_1057_1060",
    "internal_id": 6,
    "true_label": "学生发言",
    "pred_label": "教师巡视",
    "true_idx": 1,
    "pred_idx": 3
  },
  {
    "sample_id": "T17_0773_0777",
    "internal_id": 1355,
    "true_label": "技术操作",
    "pred_label": "教师指令",
    "true_idx": 7,
    "pred_idx": 4
  },
  {
    "sample_id": "T17_0533_0536",
    "internal_id": 1164,
    "true_label": "教师巡视",
    "pred_label": "课堂沉寂",
    "true_idx": 3,
    "pred_idx": 9
  },
  {
    "sample_id": "T18_0091_0095",
    "internal_id": 269,
    "true_label": "教师巡视",
    "pred_label": "课堂沉寂",
    "true_idx": 3,
    "pred_idx": 9
  },
  {
    "sample_id": "T03_1252_1255",
    "internal_id": 3170,
    "true_label": "教师巡视",
    "pred_label": "课堂沉寂",
    "true_idx": 3,
    "pred_idx": 9
  },
  {
    "sample_id": "T32_0950_0953",
    "internal_id": 1446,
    "true_label": "教师提问",
    "pred_label": "教师巡视",
    "true_idx": 0,
    "pred_idx": 3
  },
  {
    "sample_id": "T17_0984_0987",
    "internal_id": 3870,
    "true_label": "学生发言",
    "pred_label": "课堂沉寂",
    "true_idx": 1,
    "pred_idx": 9
  },
  {
    "sample_id": "T18_0100_0105",
    "internal_id": 4374,
    "true_label": "教师巡视",
    "pred_label": "课堂沉寂",
    "true_idx": 3,
    "pred_idx": 9
  },
  {
    "sample_id": "T21_0003_0006",
    "internal_id": 3763,
    "true_label": "教师讲授",
    "pred_label": "教师板书",
    "true_idx": 2,
    "pred_idx": 5
  },
  {
    "sample_id": "T15_1707_1710",
    "internal_id": 1652,
    "true_label": "教师指令",
    "pred_label": "学生讨论",
    "true_idx": 4,
    "pred_idx": 8
  },
  {
    "sample_id": "T16_1767_1770",
    "internal_id": 424,
    "true_label": "教师指令",
    "pred_label": "学生讨论",
    "true_idx": 4,
    "pred_idx": 8
  },
  {
    "sample_id": "T19_0351_0354",
    "internal_id": 2219,
    "true_label": "教师巡视",
    "pred_label": "课堂沉寂",
    "true_idx": 3,
    "pred_idx": 9
  },
  {
    "sample_id": "T11_2158_2162",
    "internal_id": 3031,
    "true_label": "教师讲授",
    "pred_label": "学生讨论",
    "true_idx": 2,
    "pred_idx": 8
  },
  {
    "sample_id": "T04_0419_0424",
    "internal_id": 2964,
    "true_label": "教师板书",
    "pred_label": "课堂沉寂",
    "true_idx": 5,
    "pred_idx": 9
  },
  {
    "sample_id": "T30_2279_2282",
    "internal_id": 1664,
    "true_label": "教师巡视",
    "pred_label": "课堂沉寂",
    "true_idx": 3,
    "pred_idx": 9
  },
  {
    "sample_id": "T16_0344_0348",
    "internal_id": 2311,
    "true_label": "教师指令",
    "pred_label": "学生讨论",
    "true_idx": 4,
    "pred_idx": 8
  },
  {
    "sample_id": "T32_0182_0186",
    "internal_id": 127,
    "true_label": "教师讲授",
    "pred_label": "学生发言",
    "true_idx": 2,
    "pred_idx": 1
  },
  {
    "sample_id": "T13_0138_0141",
    "internal_id": 4147,
    "true_label": "教师板书",
    "pred_label": "教师巡视",
    "true_idx": 5,
    "pred_idx": 3
  },
  {
    "sample_id": "T19_2168_2172",
    "internal_id": 464,
    "true_label": "教师板书",
    "pred_label": "课堂沉寂",
    "true_idx": 5,
    "pred_idx": 9
  },
  {
    "sample_id": "T03_2148_2152",
    "internal_id": 3419,
    "true_label": "教师巡视",
    "pred_label": "教师板书",
    "true_idx": 3,
    "pred_idx": 5
  },
  {
    "sample_id": "T04_1203_1207",
    "internal_id": 4215,
    "true_label": "教师巡视",
    "pred_label": "课堂沉寂",
    "true_idx": 3,
    "pred_idx": 9
  },
  {
    "sample_id": "T32_0248_0252",
    "internal_id": 3303,
    "true_label": "教师讲授",
    "pred_label": "学生发言",
    "true_idx": 2,
    "pred_idx": 1
  },
  {
    "sample_id": "T30_2337_2341",
    "internal_id": 2974,
    "true_label": "技术操作",
    "pred_label": "课堂沉寂",
    "true_idx": 7,
    "pred_idx": 9
  },
  {
    "sample_id": "T18_1433_1437",
    "internal_id": 2412,
    "true_label": "教师巡视",
    "pred_label": "课堂沉寂",
    "true_idx": 3,
    "pred_idx": 9
  },
  {
    "sample_id": "T32_1282_1287",
    "internal_id": 352,
    "true_label": "教师巡视",
    "pred_label": "课堂沉寂",
    "true_idx": 3,
    "pred_idx": 9
  },
  {
    "sample_id": "T13_0560_0564",
    "internal_id": 2842,
    "true_label": "教师巡视",
    "pred_label": "教师板书",
    "true_idx": 3,
    "pred_idx": 5
  },
  {
    "sample_id": "T13_1293_1298",
    "internal_id": 140,
    "true_label": "教师巡视",
    "pred_label": "课堂沉寂",
    "true_idx": 3,
    "pred_idx": 9
  },
  {
    "sample_id": "T32_0071_0077",
    "internal_id": 2509,
    "true_label": "学生发言",
    "pred_label": "教师讲授",
    "true_idx": 1,
    "pred_idx": 2
  },
  {
    "sample_id": "T11_0876_0879",
    "internal_id": 4292,
    "true_label": "课堂沉寂",
    "pred_label": "学生发言",
    "true_idx": 9,
    "pred_idx": 1
  },
  {
    "sample_id": "T12_0474_0478",
    "internal_id": 3650,
    "true_label": "教师巡视",
    "pred_label": "课堂沉寂",
    "true_idx": 3,
    "pred_idx": 9
  },
  {
    "sample_id": "T03_2131_2134",
    "internal_id": 1949,
    "true_label": "教师巡视",
    "pred_label": "教师板书",
    "true_idx": 3,
    "pred_idx": 5
  },
  {
    "sample_id": "T31_1077_1082",
    "internal_id": 2889,
    "true_label": "教师讲授",
    "pred_label": "学生发言",
    "true_idx": 2,
    "pred_idx": 1
  },
  {
    "sample_id": "T17_0564_0567",
    "internal_id": 1370,
    "true_label": "教师巡视",
    "pred_label": "课堂沉寂",
    "true_idx": 3,
    "pred_idx": 9
  },
  {
    "sample_id": "T03_2561_2564",
    "internal_id": 2326,
    "true_label": "教师指令",
    "pred_label": "教师讲授",
    "true_idx": 4,
    "pred_idx": 2
  },
  {
    "sample_id": "T32_1804_1807",
    "internal_id": 386,
    "true_label": "教师巡视",
    "pred_label": "课堂沉寂",
    "true_idx": 3,
    "pred_idx": 9
  },
  {
    "sample_id": "T03_1715_1719",
    "internal_id": 3235,
    "true_label": "教师巡视",
    "pred_label": "课堂沉寂",
    "true_idx": 3,
    "pred_idx": 9
  },
  {
    "sample_id": "T11_1249_1253",
    "internal_id": 2621,
    "true_label": "教师巡视",
    "pred_label": "教师板书",
    "true_idx": 3,
    "pred_idx": 5
  },
  {
    "sample_id": "T21_1254_1258",
    "internal_id": 2057,
    "true_label": "教师反馈",
    "pred_label": "教师讲授",
    "true_idx": 6,
    "pred_idx": 2
  },
  {
    "sample_id": "T30_1688_1691",
    "internal_id": 2557,
    "true_label": "教师反馈",
    "pred_label": "学生发言",
    "true_idx": 6,
    "pred_idx": 1
  },
  {
    "sample_id": "T17_0746_0751",
    "internal_id": 2258,
    "true_label": "学生发言",
    "pred_label": "课堂沉寂",
    "true_idx": 1,
    "pred_idx": 9
  },
  {
    "sample_id": "T30_0620_0624",
    "internal_id": 525,
    "true_label": "学生发言",
    "pred_label": "课堂沉寂",
    "true_idx": 1,
    "pred_idx": 9
  },
  {
    "sample_id": "T19_2535_2540",
    "internal_id": 1670,
    "true_label": "教师指令",
    "pred_label": "教师讲授",
    "true_idx": 4,
    "pred_idx": 2
  },
  {
    "sample_id": "T21_2634_2640",
    "internal_id": 3738,
    "true_label": "教师指令",
    "pred_label": "教师讲授",
    "true_idx": 4,
    "pred_idx": 2
  },
  {
    "sample_id": "T15_0382_0386",
    "internal_id": 3332,
    "true_label": "教师反馈",
    "pred_label": "教师板书",
    "true_idx": 6,
    "pred_idx": 5
  },
  {
    "sample_id": "T14_0077_0081",
    "internal_id": 3730,
    "true_label": "教师反馈",
    "pred_label": "学生发言",
    "true_idx": 6,
    "pred_idx": 1
  },
  {
    "sample_id": "T17_0801_0806",
    "internal_id": 2111,
    "true_label": "教师板书",
    "pred_label": "教师讲授",
    "true_idx": 5,
    "pred_idx": 2
  },
  {
    "sample_id": "T32_0997_1002",
    "internal_id": 2602,
    "true_label": "教师巡视",
    "pred_label": "学生发言",
    "true_idx": 3,
    "pred_idx": 1
  },
  {
    "sample_id": "T16_0157_0160",
    "internal_id": 967,
    "true_label": "技术操作",
    "pred_label": "教师讲授",
    "true_idx": 7,
    "pred_idx": 2
  },
  {
    "sample_id": "T17_1717_1721",
    "internal_id": 3069,
    "true_label": "技术操作",
    "pred_label": "教师板书",
    "true_idx": 7,
    "pred_idx": 5
  },
  {
    "sample_id": "T03_1243_1246",
    "internal_id": 1501,
    "true_label": "教师巡视",
    "pred_label": "课堂沉寂",
    "true_idx": 3,
    "pred_idx": 9
  },
  {
    "sample_id": "T03_1246_1249",
    "internal_id": 964,
    "true_label": "教师巡视",
    "pred_label": "课堂沉寂",
    "true_idx": 3,
    "pred_idx": 9
  },
  {
    "sample_id": "T02_0158_0162",
    "internal_id": 1435,
    "true_label": "教师讲授",
    "pred_label": "学生发言",
    "true_idx": 2,
    "pred_idx": 1
  },
  {
    "sample_id": "T18_1007_1012",
    "internal_id": 3933,
    "true_label": "教师讲授",
    "pred_label": "学生发言",
    "true_idx": 2,
    "pred_idx": 1
  },
  {
    "sample_id": "T08_0939_0943",
    "internal_id": 3527,
    "true_label": "教师巡视",
    "pred_label": "课堂沉寂",
    "true_idx": 3,
    "pred_idx": 9
  },
  {
    "sample_id": "T11_0826_0830",
    "internal_id": 4343,
    "true_label": "教师巡视",
    "pred_label": "课堂沉寂",
    "true_idx": 3,
    "pred_idx": 9
  },
  {
    "sample_id": "T08_1455_1459",
    "internal_id": 1327,
    "true_label": "教师板书",
    "pred_label": "课堂沉寂",
    "true_idx": 5,
    "pred_idx": 9
  },
  {
    "sample_id": "T05_0015_0018",
    "internal_id": 4346,
    "true_label": "技术操作",
    "pred_label": "教师板书",
    "true_idx": 7,
    "pred_idx": 5
  },
  {
    "sample_id": "T18_1491_1495",
    "internal_id": 1826,
    "true_label": "教师巡视",
    "pred_label": "教师板书",
    "true_idx": 3,
    "pred_idx": 5
  },
  {
    "sample_id": "T05_1694_1698",
    "internal_id": 3276,
    "true_label": "教师板书",
    "pred_label": "课堂沉寂",
    "true_idx": 5,
    "pred_idx": 9
  },
  {
    "sample_id": "T16_1196_1200",
    "internal_id": 1846,
    "true_label": "教师巡视",
    "pred_label": "教师讲授",
    "true_idx": 3,
    "pred_idx": 2
  },
  {
    "sample_id": "T02_1221_1225",
    "internal_id": 1212,
    "true_label": "教师巡视",
    "pred_label": "教师板书",
    "true_idx": 3,
    "pred_idx": 5
  },
  {
    "sample_id": "T16_2017_2021",
    "internal_id": 3595,
    "true_label": "教师巡视",
    "pred_label": "课堂沉寂",
    "true_idx": 3,
    "pred_idx": 9
  },
  {
    "sample_id": "T05_0041_0047",
    "internal_id": 2817,
    "true_label": "教师讲授",
    "pred_label": "学生发言",
    "true_idx": 2,
    "pred_idx": 1
  },
  {
    "sample_id": "T05_2089_2095",
    "internal_id": 2555,
    "true_label": "教师板书",
    "pred_label": "课堂沉寂",
    "true_idx": 5,
    "pred_idx": 9
  },
  {
    "sample_id": "T11_2077_2081",
    "internal_id": 2008,
    "true_label": "教师讲授",
    "pred_label": "学生发言",
    "true_idx": 2,
    "pred_idx": 1
  },
  {
    "sample_id": "T13_1261_1267",
    "internal_id": 3124,
    "true_label": "教师巡视",
    "pred_label": "课堂沉寂",
    "true_idx": 3,
    "pred_idx": 9
  },
  {
    "sample_id": "T11_1244_1249",
    "internal_id": 1819,
    "true_label": "教师巡视",
    "pred_label": "课堂沉寂",
    "true_idx": 3,
    "pred_idx": 9
  },
  {
    "sample_id": "T18_1408_1412",
    "internal_id": 185,
    "true_label": "教师巡视",
    "pred_label": "课堂沉寂",
    "true_idx": 3,
    "pred_idx": 9
  },
  {
    "sample_id": "T17_0544_0547",
    "internal_id": 3245,
    "true_label": "教师巡视",
    "pred_label": "课堂沉寂",
    "true_idx": 3,
    "pred_idx": 9
  },
  {
    "sample_id": "T32_0941_0944",
    "internal_id": 3683,
    "true_label": "教师讲授",
    "pred_label": "学生发言",
    "true_idx": 2,
    "pred_idx": 1
  },
  {
    "sample_id": "T07_0940_0945",
    "internal_id": 363,
    "true_label": "教师巡视",
    "pred_label": "课堂沉寂",
    "true_idx": 3,
    "pred_idx": 9
  },
  {
    "sample_id": "T07_0408_0414",
    "internal_id": 2872,
    "true_label": "教师讲授",
    "pred_label": "技术操作",
    "true_idx": 2,
    "pred_idx": 7
  },
  {
    "sample_id": "T19_2019_2024",
    "internal_id": 1123,
    "true_label": "教师巡视",
    "pred_label": "课堂沉寂",
    "true_idx": 3,
    "pred_idx": 9
  },
  {
    "sample_id": "T10_0649_0652",
    "internal_id": 1320,
    "true_label": "教师巡视",
    "pred_label": "课堂沉寂",
    "true_idx": 3,
    "pred_idx": 9
  },
  {
    "sample_id": "T16_0129_0133",
    "internal_id": 2230,
    "true_label": "教师提问",
    "pred_label": "教师讲授",
    "true_idx": 0,
    "pred_idx": 2
  },
  {
    "sample_id": "T01_0942_0946",
    "internal_id": 517,
    "true_label": "教师指令",
    "pred_label": "技术操作",
    "true_idx": 4,
    "pred_idx": 7
  },
  {
    "sample_id": "T32_0160_0163",
    "internal_id": 3156,
    "true_label": "教师讲授",
    "pred_label": "学生发言",
    "true_idx": 2,
    "pred_idx": 1
  },
  {
    "sample_id": "T04_2024_2028",
    "internal_id": 4307,
    "true_label": "教师板书",
    "pred_label": "技术操作",
    "true_idx": 5,
    "pred_idx": 7
  },
  {
    "sample_id": "T30_0361_0366",
    "internal_id": 773,
    "true_label": "教师讲授",
    "pred_label": "教师指令",
    "true_idx": 2,
    "pred_idx": 4
  },
  {
    "sample_id": "T13_0772_0778",
    "internal_id": 4192,
    "true_label": "教师板书",
    "pred_label": "课堂沉寂",
    "true_idx": 5,
    "pred_idx": 9
  },
  {
    "sample_id": "T04_1132_1136",
    "internal_id": 3335,
    "true_label": "教师巡视",
    "pred_label": "课堂沉寂",
    "true_idx": 3,
    "pred_idx": 9
  },
  {
    "sample_id": "T30_0494_0500",
    "internal_id": 72,
    "true_label": "教师讲授",
    "pred_label": "学生发言",
    "true_idx": 2,
    "pred_idx": 1
  },
  {
    "sample_id": "T04_0281_0284",
    "internal_id": 563,
    "true_label": "教师巡视",
    "pred_label": "课堂沉寂",
    "true_idx": 3,
    "pred_idx": 9
  },
  {
    "sample_id": "T05_2260_2266",
    "internal_id": 1505,
    "true_label": "教师巡视",
    "pred_label": "课堂沉寂",
    "true_idx": 3,
    "pred_idx": 9
  },
  {
    "sample_id": "T32_0968_0973",
    "internal_id": 2074,
    "true_label": "教师巡视",
    "pred_label": "教师提问",
    "true_idx": 3,
    "pred_idx": 0
  },
  {
    "sample_id": "T04_0235_0238",
    "internal_id": 2704,
    "true_label": "教师讲授",
    "pred_label": "学生发言",
    "true_idx": 2,
    "pred_idx": 1
  },
  {
    "sample_id": "T21_0163_0166",
    "internal_id": 2636,
    "true_label": "教师板书",
    "pred_label": "技术操作",
    "true_idx": 5,
    "pred_idx": 7
  },
  {
    "sample_id": "T19_1464_1468",
    "internal_id": 3574,
    "true_label": "教师板书",
    "pred_label": "技术操作",
    "true_idx": 5,
    "pred_idx": 7
  },
  {
    "sample_id": "T32_1321_1323",
    "internal_id": 2549,
    "true_label": "教师巡视",
    "pred_label": "课堂沉寂",
    "true_idx": 3,
    "pred_idx": 9
  },
  {
    "sample_id": "T04_1245_1248",
    "internal_id": 2522,
    "true_label": "教师巡视",
    "pred_label": "课堂沉寂",
    "true_idx": 3,
    "pred_idx": 9
  },
  {
    "sample_id": "T31_0188_0191",
    "internal_id": 656,
    "true_label": "学生发言",
    "pred_label": "学生讨论",
    "true_idx": 1,
    "pred_idx": 8
  },
  {
    "sample_id": "T30_0150_0153",
    "internal_id": 3776,
    "true_label": "教师讲授",
    "pred_label": "技术操作",
    "true_idx": 2,
    "pred_idx": 7
  },
  {
    "sample_id": "T19_2010_2015",
    "internal_id": 1194,
    "true_label": "教师巡视",
    "pred_label": "课堂沉寂",
    "true_idx": 3,
    "pred_idx": 9
  },
  {
    "sample_id": "T11_0622_0626",
    "internal_id": 1730,
    "true_label": "教师板书",
    "pred_label": "技术操作",
    "true_idx": 5,
    "pred_idx": 7
  },
  {
    "sample_id": "T16_0741_0745",
    "internal_id": 3580,
    "true_label": "教师巡视",
    "pred_label": "教师讲授",
    "true_idx": 3,
    "pred_idx": 2
  },
  {
    "sample_id": "T05_0129_0134",
    "internal_id": 2907,
    "true_label": "教师板书",
    "pred_label": "教师巡视",
    "true_idx": 5,
    "pred_idx": 3
  },
  {
    "sample_id": "T08_0525_0530",
    "internal_id": 3293,
    "true_label": "教师板书",
    "pred_label": "课堂沉寂",
    "true_idx": 5,
    "pred_idx": 9
  },
  {
    "sample_id": "T04_0595_0599",
    "internal_id": 591,
    "true_label": "教师指令",
    "pred_label": "教师讲授",
    "true_idx": 4,
    "pred_idx": 2
  },
  {
    "sample_id": "T21_0637_0642",
    "internal_id": 2516,
    "true_label": "教师巡视",
    "pred_label": "课堂沉寂",
    "true_idx": 3,
    "pred_idx": 9
  },
  {
    "sample_id": "T04_0731_0735",
    "internal_id": 2688,
    "true_label": "教师讲授",
    "pred_label": "教师指令",
    "true_idx": 2,
    "pred_idx": 4
  },
  {
    "sample_id": "T19_2085_2088",
    "internal_id": 1562,
    "true_label": "教师板书",
    "pred_label": "课堂沉寂",
    "true_idx": 5,
    "pred_idx": 9
  },
  {
    "sample_id": "T18_1452_1455",
    "internal_id": 281,
    "true_label": "课堂沉寂",
    "pred_label": "教师巡视",
    "true_idx": 9,
    "pred_idx": 3
  },
  {
    "sample_id": "T07_0816_0819",
    "internal_id": 1838,
    "true_label": "教师提问",
    "pred_label": "教师讲授",
    "true_idx": 0,
    "pred_idx": 2
  },
  {
    "sample_id": "T20_2284_2289",
    "internal_id": 607,
    "true_label": "技术操作",
    "pred_label": "教师讲授",
    "true_idx": 7,
    "pred_idx": 2
  },
  {
    "sample_id": "T07_0239_0244",
    "internal_id": 2924,
    "true_label": "教师指令",
    "pred_label": "教师讲授",
    "true_idx": 4,
    "pred_idx": 2
  },
  {
    "sample_id": "T17_0842_0848",
    "internal_id": 3873,
    "true_label": "教师板书",
    "pred_label": "课堂沉寂",
    "true_idx": 5,
    "pred_idx": 9
  },
  {
    "sample_id": "T02_0483_0488",
    "internal_id": 3427,
    "true_label": "教师巡视",
    "pred_label": "课堂沉寂",
    "true_idx": 3,
    "pred_idx": 9
  },
  {
    "sample_id": "T32_0092_0097",
    "internal_id": 1753,
    "true_label": "学生发言",
    "pred_label": "教师讲授",
    "true_idx": 1,
    "pred_idx": 2
  },
  {
    "sample_id": "T01_0811_0816",
    "internal_id": 1991,
    "true_label": "教师巡视",
    "pred_label": "课堂沉寂",
    "true_idx": 3,
    "pred_idx": 9
  },
  {
    "sample_id": "T11_0665_0669",
    "internal_id": 1295,
    "true_label": "教师板书",
    "pred_label": "技术操作",
    "true_idx": 5,
    "pred_idx": 7
  },
  {
    "sample_id": "T07_0480_0485",
    "internal_id": 1491,
    "true_label": "教师巡视",
    "pred_label": "教师讲授",
    "true_idx": 3,
    "pred_idx": 2
  },
  {
    "sample_id": "T30_0547_0551",
    "internal_id": 3208,
    "true_label": "学生发言",
    "pred_label": "教师讲授",
    "true_idx": 1,
    "pred_idx": 2
  },
  {
    "sample_id": "T31_0852_0855",
    "internal_id": 2701,
    "true_label": "学生讨论",
    "pred_label": "学生发言",
    "true_idx": 8,
    "pred_idx": 1
  },
  {
    "sample_id": "T15_1796_1802",
    "internal_id": 739,
    "true_label": "教师巡视",
    "pred_label": "课堂沉寂",
    "true_idx": 3,
    "pred_idx": 9
  },
  {
    "sample_id": "T05_0857_0860",
    "internal_id": 228,
    "true_label": "教师巡视",
    "pred_label": "课堂沉寂",
    "true_idx": 3,
    "pred_idx": 9
  },
  {
    "sample_id": "T16_2064_2068",
    "internal_id": 534,
    "true_label": "教师指令",
    "pred_label": "教师讲授",
    "true_idx": 4,
    "pred_idx": 2
  },
  {
    "sample_id": "T16_2451_2454",
    "internal_id": 734,
    "true_label": "教师提问",
    "pred_label": "教师讲授",
    "true_idx": 0,
    "pred_idx": 2
  },
  {
    "sample_id": "T18_1455_1458",
    "internal_id": 657,
    "true_label": "教师巡视",
    "pred_label": "课堂沉寂",
    "true_idx": 3,
    "pred_idx": 9
  },
  {
    "sample_id": "T20_1593_1597",
    "internal_id": 709,
    "true_label": "教师指令",
    "pred_label": "教师讲授",
    "true_idx": 4,
    "pred_idx": 2
  },
  {
    "sample_id": "T11_1347_1352",
    "internal_id": 1934,
    "true_label": "教师巡视",
    "pred_label": "课堂沉寂",
    "true_idx": 3,
    "pred_idx": 9
  },
  {
    "sample_id": "T18_1468_1471",
    "internal_id": 4121,
    "true_label": "教师巡视",
    "pred_label": "课堂沉寂",
    "true_idx": 3,
    "pred_idx": 9
  },
  {
    "sample_id": "T16_2251_2255",
    "internal_id": 469,
    "true_label": "教师巡视",
    "pred_label": "课堂沉寂",
    "true_idx": 3,
    "pred_idx": 9
  },
  {
    "sample_id": "T09_0424_0429",
    "internal_id": 3116,
    "true_label": "教师板书",
    "pred_label": "课堂沉寂",
    "true_idx": 5,
    "pred_idx": 9
  },
  {
    "sample_id": "T18_0579_0583",
    "internal_id": 4416,
    "true_label": "教师板书",
    "pred_label": "课堂沉寂",
    "true_idx": 5,
    "pred_idx": 9
  },
  {
    "sample_id": "T20_2517_2520",
    "internal_id": 1777,
    "true_label": "技术操作",
    "pred_label": "教师讲授",
    "true_idx": 7,
    "pred_idx": 2
  },
  {
    "sample_id": "T30_1666_1671",
    "internal_id": 4093,
    "true_label": "学生发言",
    "pred_label": "课堂沉寂",
    "true_idx": 1,
    "pred_idx": 9
  },
  {
    "sample_id": "T32_2003_2007",
    "internal_id": 2705,
    "true_label": "教师巡视",
    "pred_label": "课堂沉寂",
    "true_idx": 3,
    "pred_idx": 9
  },
  {
    "sample_id": "T01_1290_1295",
    "internal_id": 3437,
    "true_label": "教师指令",
    "pred_label": "课堂沉寂",
    "true_idx": 4,
    "pred_idx": 9
  },
  {
    "sample_id": "T18_2130_2134",
    "internal_id": 1970,
    "true_label": "教师板书",
    "pred_label": "教师讲授",
    "true_idx": 5,
    "pred_idx": 2
  },
  {
    "sample_id": "T30_0590_0593",
    "internal_id": 4247,
    "true_label": "学生发言",
    "pred_label": "课堂沉寂",
    "true_idx": 1,
    "pred_idx": 9
  },
  {
    "sample_id": "T30_0877_0883",
    "internal_id": 3991,
    "true_label": "教师提问",
    "pred_label": "教师讲授",
    "true_idx": 0,
    "pred_idx": 2
  },
  {
    "sample_id": "T08_0090_0095",
    "internal_id": 4168,
    "true_label": "教师板书",
    "pred_label": "技术操作",
    "true_idx": 5,
    "pred_idx": 7
  },
  {
    "sample_id": "T05_2077_2081",
    "internal_id": 689,
    "true_label": "教师板书",
    "pred_label": "课堂沉寂",
    "true_idx": 5,
    "pred_idx": 9
  },
  {
    "sample_id": "T09_0789_0793",
    "internal_id": 2081,
    "true_label": "教师指令",
    "pred_label": "教师讲授",
    "true_idx": 4,
    "pred_idx": 2
  },
  {
    "sample_id": "T20_2119_2123",
    "internal_id": 721,
    "true_label": "教师反馈",
    "pred_label": "教师巡视",
    "true_idx": 6,
    "pred_idx": 3
  },
  {
    "sample_id": "T32_0576_0579",
    "internal_id": 1906,
    "true_label": "教师反馈",
    "pred_label": "学生发言",
    "true_idx": 6,
    "pred_idx": 1
  },
  {
    "sample_id": "T07_0501_0504",
    "internal_id": 1167,
    "true_label": "教师巡视",
    "pred_label": "学生发言",
    "true_idx": 3,
    "pred_idx": 1
  },
  {
    "sample_id": "T21_0236_0241",
    "internal_id": 682,
    "true_label": "教师反馈",
    "pred_label": "教师讲授",
    "true_idx": 6,
    "pred_idx": 2
  },
  {
    "sample_id": "T04_1241_1245",
    "internal_id": 4020,
    "true_label": "教师巡视",
    "pred_label": "课堂沉寂",
    "true_idx": 3,
    "pred_idx": 9
  },
  {
    "sample_id": "T11_1352_1357",
    "internal_id": 3898,
    "true_label": "教师巡视",
    "pred_label": "课堂沉寂",
    "true_idx": 3,
    "pred_idx": 9
  },
  {
    "sample_id": "T19_2005_2010",
    "internal_id": 1721,
    "true_label": "教师巡视",
    "pred_label": "课堂沉寂",
    "true_idx": 3,
    "pred_idx": 9
  },
  {
    "sample_id": "T19_0363_0366",
    "internal_id": 1595,
    "true_label": "教师巡视",
    "pred_label": "课堂沉寂",
    "true_idx": 3,
    "pred_idx": 9
  },
  {
    "sample_id": "T32_0442_0448",
    "internal_id": 3202,
    "true_label": "教师讲授",
    "pred_label": "学生发言",
    "true_idx": 2,
    "pred_idx": 1
  },
  {
    "sample_id": "T30_0349_0353",
    "internal_id": 420,
    "true_label": "教师指令",
    "pred_label": "教师讲授",
    "true_idx": 4,
    "pred_idx": 2
  },
  {
    "sample_id": "T20_0122_0125",
    "internal_id": 265,
    "true_label": "教师板书",
    "pred_label": "教师巡视",
    "true_idx": 5,
    "pred_idx": 3
  },
  {
    "sample_id": "T16_1172_1176",
    "internal_id": 1782,
    "true_label": "教师巡视",
    "pred_label": "学生发言",
    "true_idx": 3,
    "pred_idx": 1
  },
  {
    "sample_id": "T30_1757_1760",
    "internal_id": 1186,
    "true_label": "教师指令",
    "pred_label": "教师讲授",
    "true_idx": 4,
    "pred_idx": 2
  },
  {
    "sample_id": "T32_1002_1007",
    "internal_id": 1152,
    "true_label": "教师巡视",
    "pred_label": "教师板书",
    "true_idx": 3,
    "pred_idx": 5
  },
  {
    "sample_id": "T01_0164_0168",
    "internal_id": 1016,
    "true_label": "技术操作",
    "pred_label": "教师板书",
    "true_idx": 7,
    "pred_idx": 5
  },
  {
    "sample_id": "T04_1918_1923",
    "internal_id": 2182,
    "true_label": "教师反馈",
    "pred_label": "教师讲授",
    "true_idx": 6,
    "pred_idx": 2
  },
  {
    "sample_id": "T18_2073_2076",
    "internal_id": 2318,
    "true_label": "教师讲授",
    "pred_label": "教师板书",
    "true_idx": 2,
    "pred_idx": 5
  },
  {
    "sample_id": "T18_2175_2179",
    "internal_id": 3327,
    "true_label": "教师板书",
    "pred_label": "教师讲授",
    "true_idx": 5,
    "pred_idx": 2
  },
  {
    "sample_id": "T05_0145_0151",
    "internal_id": 2660,
    "true_label": "教师板书",
    "pred_label": "教师讲授",
    "true_idx": 5,
    "pred_idx": 2
  },
  {
    "sample_id": "T21_0155_0159",
    "internal_id": 3632,
    "true_label": "教师板书",
    "pred_label": "教师讲授",
    "true_idx": 5,
    "pred_idx": 2
  },
  {
    "sample_id": "T09_1713_1716",
    "internal_id": 3104,
    "true_label": "教师巡视",
    "pred_label": "课堂沉寂",
    "true_idx": 3,
    "pred_idx": 9
  },
  {
    "sample_id": "T18_0077_0081",
    "internal_id": 1334,
    "true_label": "教师巡视",
    "pred_label": "课堂沉寂",
    "true_idx": 3,
    "pred_idx": 9
  },
  {
    "sample_id": "T03_2181_2184",
    "internal_id": 662,
    "true_label": "教师巡视",
    "pred_label": "教师板书",
    "true_idx": 3,
    "pred_idx": 5
  },
  {
    "sample_id": "T14_2045_2049",
    "internal_id": 3126,
    "true_label": "教师板书",
    "pred_label": "学生发言",
    "true_idx": 5,
    "pred_idx": 1
  },
  {
    "sample_id": "T18_0508_0512",
    "internal_id": 2199,
    "true_label": "教师巡视",
    "pred_label": "课堂沉寂",
    "true_idx": 3,
    "pred_idx": 9
  },
  {
    "sample_id": "T03_0009_0012",
    "internal_id": 3477,
    "true_label": "教师指令",
    "pred_label": "教师反馈",
    "true_idx": 4,
    "pred_idx": 6
  },
  {
    "sample_id": "T32_1752_1757",
    "internal_id": 2226,
    "true_label": "教师巡视",
    "pred_label": "教师板书",
    "true_idx": 3,
    "pred_idx": 5
  },
  {
    "sample_id": "T19_0797_0803",
    "internal_id": 3287,
    "true_label": "技术操作",
    "pred_label": "教师板书",
    "true_idx": 7,
    "pred_idx": 5
  },
  {
    "sample_id": "T19_2029_2034",
    "internal_id": 4267,
    "true_label": "教师巡视",
    "pred_label": "课堂沉寂",
    "true_idx": 3,
    "pred_idx": 9
  },
  {
    "sample_id": "T30_0016_0022",
    "internal_id": 1105,
    "true_label": "教师讲授",
    "pred_label": "教师反馈",
    "true_idx": 2,
    "pred_idx": 6
  },
  {
    "sample_id": "T12_0478_0482",
    "internal_id": 1522,
    "true_label": "教师巡视",
    "pred_label": "课堂沉寂",
    "true_idx": 3,
    "pred_idx": 9
  },
  {
    "sample_id": "T18_0058_0063",
    "internal_id": 342,
    "true_label": "教师巡视",
    "pred_label": "教师讲授",
    "true_idx": 3,
    "pred_idx": 2
  },
  {
    "sample_id": "T01_1461_1466",
    "internal_id": 987,
    "true_label": "教师指令",
    "pred_label": "学生发言",
    "true_idx": 4,
    "pred_idx": 1
  },
  {
    "sample_id": "T02_0477_0483",
    "internal_id": 329,
    "true_label": "教师巡视",
    "pred_label": "课堂沉寂",
    "true_idx": 3,
    "pred_idx": 9
  },
  {
    "sample_id": "T16_1148_1153",
    "internal_id": 1137,
    "true_label": "教师巡视",
    "pred_label": "教师讲授",
    "true_idx": 3,
    "pred_idx": 2
  },
  {
    "sample_id": "T21_1328_1334",
    "internal_id": 810,
    "true_label": "教师讲授",
    "pred_label": "教师提问",
    "true_idx": 2,
    "pred_idx": 0
  },
  {
    "sample_id": "T30_0162_0165",
    "internal_id": 896,
    "true_label": "教师讲授",
    "pred_label": "学生讨论",
    "true_idx": 2,
    "pred_idx": 8
  },
  {
    "sample_id": "T18_0086_0091",
    "internal_id": 2821,
    "true_label": "教师巡视",
    "pred_label": "课堂沉寂",
    "true_idx": 3,
    "pred_idx": 9
  },
  {
    "sample_id": "T16_2269_2275",
    "internal_id": 3267,
    "true_label": "教师巡视",
    "pred_label": "课堂沉寂",
    "true_idx": 3,
    "pred_idx": 9
  },
  {
    "sample_id": "T18_0469_0474",
    "internal_id": 1426,
    "true_label": "教师巡视",
    "pred_label": "课堂沉寂",
    "true_idx": 3,
    "pred_idx": 9
  },
  {
    "sample_id": "T04_0275_0278",
    "internal_id": 1554,
    "true_label": "教师巡视",
    "pred_label": "课堂沉寂",
    "true_idx": 3,
    "pred_idx": 9
  },
  {
    "sample_id": "T03_2139_2143",
    "internal_id": 478,
    "true_label": "教师巡视",
    "pred_label": "课堂沉寂",
    "true_idx": 3,
    "pred_idx": 9
  },
  {
    "sample_id": "T21_1371_1376",
    "internal_id": 627,
    "true_label": "教师巡视",
    "pred_label": "课堂沉寂",
    "true_idx": 3,
    "pred_idx": 9
  },
  {
    "sample_id": "T12_0144_0147",
    "internal_id": 4071,
    "true_label": "教师指令",
    "pred_label": "教师讲授",
    "true_idx": 4,
    "pred_idx": 2
  },
  {
    "sample_id": "T32_0241_0245",
    "internal_id": 4287,
    "true_label": "教师讲授",
    "pred_label": "学生发言",
    "true_idx": 2,
    "pred_idx": 1
  },
  {
    "sample_id": "T07_0092_0096",
    "internal_id": 1456,
    "true_label": "教师讲授",
    "pred_label": "学生发言",
    "true_idx": 2,
    "pred_idx": 1
  },
  {
    "sample_id": "T04_0793_0796",
    "internal_id": 636,
    "true_label": "教师巡视",
    "pred_label": "课堂沉寂",
    "true_idx": 3,
    "pred_idx": 9
  },
  {
    "sample_id": "T17_0571_0574",
    "internal_id": 2853,
    "true_label": "教师巡视",
    "pred_label": "课堂沉寂",
    "true_idx": 3,
    "pred_idx": 9
  },
  {
    "sample_id": "T04_0290_0293",
    "internal_id": 2517,
    "true_label": "教师巡视",
    "pred_label": "课堂沉寂",
    "true_idx": 3,
    "pred_idx": 9
  },
  {
    "sample_id": "T03_2081_2084",
    "internal_id": 2591,
    "true_label": "教师巡视",
    "pred_label": "课堂沉寂",
    "true_idx": 3,
    "pred_idx": 9
  },
  {
    "sample_id": "T05_2230_2235",
    "internal_id": 981,
    "true_label": "教师巡视",
    "pred_label": "教师板书",
    "true_idx": 3,
    "pred_idx": 5
  },
  {
    "sample_id": "T19_1787_1790",
    "internal_id": 2340,
    "true_label": "教师指令",
    "pred_label": "课堂沉寂",
    "true_idx": 4,
    "pred_idx": 9
  },
  {
    "sample_id": "T04_1669_1672",
    "internal_id": 4253,
    "true_label": "教师巡视",
    "pred_label": "课堂沉寂",
    "true_idx": 3,
    "pred_idx": 9
  },
  {
    "sample_id": "T07_1243_1246",
    "internal_id": 3741,
    "true_label": "教师巡视",
    "pred_label": "教师提问",
    "true_idx": 3,
    "pred_idx": 0
  },
  {
    "sample_id": "T18_1390_1393",
    "internal_id": 4393,
    "true_label": "教师巡视",
    "pred_label": "课堂沉寂",
    "true_idx": 3,
    "pred_idx": 9
  },
  {
    "sample_id": "T32_0210_0214",
    "internal_id": 1209,
    "true_label": "教师讲授",
    "pred_label": "学生发言",
    "true_idx": 2,
    "pred_idx": 1
  },
  {
    "sample_id": "T17_0424_0427",
    "internal_id": 2769,
    "true_label": "教师讲授",
    "pred_label": "学生发言",
    "true_idx": 2,
    "pred_idx": 1
  },
  {
    "sample_id": "T18_1421_1424",
    "internal_id": 3043,
    "true_label": "教师巡视",
    "pred_label": "课堂沉寂",
    "true_idx": 3,
    "pred_idx": 9
  },
  {
    "sample_id": "T21_1640_1643",
    "internal_id": 623,
    "true_label": "教师巡视",
    "pred_label": "教师板书",
    "true_idx": 3,
    "pred_idx": 5
  },
  {
    "sample_id": "T21_0642_0647",
    "internal_id": 2638,
    "true_label": "教师巡视",
    "pred_label": "课堂沉寂",
    "true_idx": 3,
    "pred_idx": 9
  },
  {
    "sample_id": "T12_0731_0734",
    "internal_id": 1925,
    "true_label": "教师反馈",
    "pred_label": "教师板书",
    "true_idx": 6,
    "pred_idx": 5
  },
  {
    "sample_id": "T32_0065_0068",
    "internal_id": 208,
    "true_label": "教师讲授",
    "pred_label": "学生发言",
    "true_idx": 2,
    "pred_idx": 1
  },
  {
    "sample_id": "T20_1759_1765",
    "internal_id": 2413,
    "true_label": "教师指令",
    "pred_label": "教师讲授",
    "true_idx": 4,
    "pred_idx": 2
  },
  {
    "sample_id": "T31_1197_1199",
    "internal_id": 2122,
    "true_label": "教师讲授",
    "pred_label": "学生发言",
    "true_idx": 2,
    "pred_idx": 1
  },
  {
    "sample_id": "T06_1151_1154",
    "internal_id": 2438,
    "true_label": "教师巡视",
    "pred_label": "课堂沉寂",
    "true_idx": 3,
    "pred_idx": 9
  },
  {
    "sample_id": "T19_0354_0357",
    "internal_id": 1626,
    "true_label": "教师巡视",
    "pred_label": "课堂沉寂",
    "true_idx": 3,
    "pred_idx": 9
  },
  {
    "sample_id": "T32_0459_0465",
    "internal_id": 3722,
    "true_label": "教师讲授",
    "pred_label": "学生发言",
    "true_idx": 2,
    "pred_idx": 1
  },
  {
    "sample_id": "T16_2280_2284",
    "internal_id": 4293,
    "true_label": "教师巡视",
    "pred_label": "教师指令",
    "true_idx": 3,
    "pred_idx": 4
  },
  {
    "sample_id": "T21_2342_2345",
    "internal_id": 2898,
    "true_label": "教师板书",
    "pred_label": "教师巡视",
    "true_idx": 5,
    "pred_idx": 3
  },
  {
    "sample_id": "T12_0061_0063",
    "internal_id": 3764,
    "true_label": "技术操作",
    "pred_label": "课堂沉寂",
    "true_idx": 7,
    "pred_idx": 9
  },
  {
    "sample_id": "T32_1293_1296",
    "internal_id": 2019,
    "true_label": "教师巡视",
    "pred_label": "课堂沉寂",
    "true_idx": 3,
    "pred_idx": 9
  },
  {
    "sample_id": "T05_0665_0669",
    "internal_id": 1891,
    "true_label": "教师巡视",
    "pred_label": "课堂沉寂",
    "true_idx": 3,
    "pred_idx": 9
  },
  {
    "sample_id": "T13_0865_0868",
    "internal_id": 3425,
    "true_label": "教师板书",
    "pred_label": "学生发言",
    "true_idx": 5,
    "pred_idx": 1
  },
  {
    "sample_id": "T32_0030_0036",
    "internal_id": 663,
    "true_label": "教师讲授",
    "pred_label": "学生发言",
    "true_idx": 2,
    "pred_idx": 1
  },
  {
    "sample_id": "T30_0186_0190",
    "internal_id": 3932,
    "true_label": "学生讨论",
    "pred_label": "学生发言",
    "true_idx": 8,
    "pred_idx": 1
  },
  {
    "sample_id": "T05_0991_0994",
    "internal_id": 4019,
    "true_label": "教师巡视",
    "pred_label": "课堂沉寂",
    "true_idx": 3,
    "pred_idx": 9
  },
  {
    "sample_id": "T21_1950_1954",
    "internal_id": 4414,
    "true_label": "教师指令",
    "pred_label": "教师巡视",
    "true_idx": 4,
    "pred_idx": 3
  },
  {
    "sample_id": "T04_1179_1184",
    "internal_id": 242,
    "true_label": "教师讲授",
    "pred_label": "学生发言",
    "true_idx": 2,
    "pred_idx": 1
  },
  {
    "sample_id": "T06_1194_1198",
    "internal_id": 70,
    "true_label": "教师板书",
    "pred_label": "课堂沉寂",
    "true_idx": 5,
    "pred_idx": 9
  },
  {
    "sample_id": "T07_0031_0035",
    "internal_id": 3866,
    "true_label": "教师板书",
    "pred_label": "教师巡视",
    "true_idx": 5,
    "pred_idx": 3
  },
  {
    "sample_id": "T04_0119_0124",
    "internal_id": 1695,
    "true_label": "教师板书",
    "pred_label": "学生发言",
    "true_idx": 5,
    "pred_idx": 1
  },
  {
    "sample_id": "T16_1157_1162",
    "internal_id": 2679,
    "true_label": "教师巡视",
    "pred_label": "教师讲授",
    "true_idx": 3,
    "pred_idx": 2
  },
  {
    "sample_id": "T04_1412_1416",
    "internal_id": 1745,
    "true_label": "教师反馈",
    "pred_label": "课堂沉寂",
    "true_idx": 6,
    "pred_idx": 9
  },
  {
    "sample_id": "T08_1316_1319",
    "internal_id": 3631,
    "true_label": "教师板书",
    "pred_label": "教师巡视",
    "true_idx": 5,
    "pred_idx": 3
  },
  {
    "sample_id": "T18_0140_0145",
    "internal_id": 2820,
    "true_label": "教师板书",
    "pred_label": "课堂沉寂",
    "true_idx": 5,
    "pred_idx": 9
  },
  {
    "sample_id": "T11_0801_0807",
    "internal_id": 1286,
    "true_label": "教师指令",
    "pred_label": "教师讲授",
    "true_idx": 4,
    "pred_idx": 2
  },
  {
    "sample_id": "T05_2173_2178",
    "internal_id": 1514,
    "true_label": "教师板书",
    "pred_label": "课堂沉寂",
    "true_idx": 5,
    "pred_idx": 9
  },
  {
    "sample_id": "T16_2533_2537",
    "internal_id": 2188,
    "true_label": "学生发言",
    "pred_label": "教师讲授",
    "true_idx": 1,
    "pred_idx": 2
  },
  {
    "sample_id": "T31_0840_0844",
    "internal_id": 1751,
    "true_label": "教师巡视",
    "pred_label": "课堂沉寂",
    "true_idx": 3,
    "pred_idx": 9
  },
  {
    "sample_id": "T02_0446_0449",
    "internal_id": 1712,
    "true_label": "课堂沉寂",
    "pred_label": "教师巡视",
    "true_idx": 9,
    "pred_idx": 3
  },
  {
    "sample_id": "T05_2081_2085",
    "internal_id": 2458,
    "true_label": "教师板书",
    "pred_label": "课堂沉寂",
    "true_idx": 5,
    "pred_idx": 9
  },
  {
    "sample_id": "T17_1369_1372",
    "internal_id": 1184,
    "true_label": "教师板书",
    "pred_label": "教师巡视",
    "true_idx": 5,
    "pred_idx": 3
  },
  {
    "sample_id": "T04_1248_1251",
    "internal_id": 647,
    "true_label": "教师巡视",
    "pred_label": "课堂沉寂",
    "true_idx": 3,
    "pred_idx": 9
  },
  {
    "sample_id": "T15_1547_1550",
    "internal_id": 2752,
    "true_label": "课堂沉寂",
    "pred_label": "学生发言",
    "true_idx": 9,
    "pred_idx": 1
  },
  {
    "sample_id": "T15_1724_1727",
    "internal_id": 1764,
    "true_label": "教师巡视",
    "pred_label": "课堂沉寂",
    "true_idx": 3,
    "pred_idx": 9
  },
  {
    "sample_id": "T30_0320_0325",
    "internal_id": 3777,
    "true_label": "教师巡视",
    "pred_label": "教师指令",
    "true_idx": 3,
    "pred_idx": 4
  },
  {
    "sample_id": "T18_1430_1433",
    "internal_id": 2950,
    "true_label": "教师巡视",
    "pred_label": "课堂沉寂",
    "true_idx": 3,
    "pred_idx": 9
  },
  {
    "sample_id": "T04_1096_1100",
    "internal_id": 3928,
    "true_label": "教师巡视",
    "pred_label": "课堂沉寂",
    "true_idx": 3,
    "pred_idx": 9
  },
  {
    "sample_id": "T03_0478_0483",
    "internal_id": 3903,
    "true_label": "教师讲授",
    "pred_label": "教师反馈",
    "true_idx": 2,
    "pred_idx": 6
  },
  {
    "sample_id": "T16_0251_0257",
    "internal_id": 3040,
    "true_label": "教师巡视",
    "pred_label": "教师提问",
    "true_idx": 3,
    "pred_idx": 0
  },
  {
    "sample_id": "T06_0064_0068",
    "internal_id": 1804,
    "true_label": "教师讲授",
    "pred_label": "学生发言",
    "true_idx": 2,
    "pred_idx": 1
  },
  {
    "sample_id": "T04_0278_0281",
    "internal_id": 3402,
    "true_label": "教师巡视",
    "pred_label": "课堂沉寂",
    "true_idx": 3,
    "pred_idx": 9
  },
  {
    "sample_id": "T04_0297_0301",
    "internal_id": 2616,
    "true_label": "教师巡视",
    "pred_label": "课堂沉寂",
    "true_idx": 3,
    "pred_idx": 9
  },
  {
    "sample_id": "T19_0366_0369",
    "internal_id": 249,
    "true_label": "教师巡视",
    "pred_label": "课堂沉寂",
    "true_idx": 3,
    "pred_idx": 9
  },
  {
    "sample_id": "T05_1794_1799",
    "internal_id": 826,
    "true_label": "教师巡视",
    "pred_label": "课堂沉寂",
    "true_idx": 3,
    "pred_idx": 9
  },
  {
    "sample_id": "T13_1795_1799",
    "internal_id": 4077,
    "true_label": "教师巡视",
    "pred_label": "课堂沉寂",
    "true_idx": 3,
    "pred_idx": 9
  },
  {
    "sample_id": "T04_1273_1277",
    "internal_id": 2281,
    "true_label": "教师巡视",
    "pred_label": "课堂沉寂",
    "true_idx": 3,
    "pred_idx": 9
  },
  {
    "sample_id": "T08_1695_1697",
    "internal_id": 3592,
    "true_label": "教师巡视",
    "pred_label": "课堂沉寂",
    "true_idx": 3,
    "pred_idx": 9
  },
  {
    "sample_id": "T14_1295_1298",
    "internal_id": 1867,
    "true_label": "教师巡视",
    "pred_label": "课堂沉寂",
    "true_idx": 3,
    "pred_idx": 9
  },
  {
    "sample_id": "T04_1136_1140",
    "internal_id": 2309,
    "true_label": "教师巡视",
    "pred_label": "课堂沉寂",
    "true_idx": 3,
    "pred_idx": 9
  },
  {
    "sample_id": "T14_1314_1318",
    "internal_id": 3990,
    "true_label": "教师巡视",
    "pred_label": "课堂沉寂",
    "true_idx": 3,
    "pred_idx": 9
  },
  {
    "sample_id": "T32_0750_0753",
    "internal_id": 2313,
    "true_label": "教师反馈",
    "pred_label": "教师巡视",
    "true_idx": 6,
    "pred_idx": 3
  },
  {
    "sample_id": "T05_1033_1036",
    "internal_id": 1787,
    "true_label": "教师巡视",
    "pred_label": "课堂沉寂",
    "true_idx": 3,
    "pred_idx": 9
  },
  {
    "sample_id": "T05_1398_1402",
    "internal_id": 4130,
    "true_label": "教师反馈",
    "pred_label": "课堂沉寂",
    "true_idx": 6,
    "pred_idx": 9
  },
  {
    "sample_id": "T30_0570_0576",
    "internal_id": 3167,
    "true_label": "教师讲授",
    "pred_label": "课堂沉寂",
    "true_idx": 2,
    "pred_idx": 9
  },
  {
    "sample_id": "T32_0252_0255",
    "internal_id": 3356,
    "true_label": "教师讲授",
    "pred_label": "学生发言",
    "true_idx": 2,
    "pred_idx": 1
  },
  {
    "sample_id": "T04_1965_1970",
    "internal_id": 4353,
    "true_label": "教师巡视",
    "pred_label": "课堂沉寂",
    "true_idx": 3,
    "pred_idx": 9
  },
  {
    "sample_id": "T04_1238_1241",
    "internal_id": 2401,
    "true_label": "教师巡视",
    "pred_label": "课堂沉寂",
    "true_idx": 3,
    "pred_idx": 9
  },
  {
    "sample_id": "T32_1997_2000",
    "internal_id": 3971,
    "true_label": "教师巡视",
    "pred_label": "课堂沉寂",
    "true_idx": 3,
    "pred_idx": 9
  },
  {
    "sample_id": "T14_0274_0277",
    "internal_id": 1223,
    "true_label": "教师巡视",
    "pred_label": "课堂沉寂",
    "true_idx": 3,
    "pred_idx": 9
  },
  {
    "sample_id": "T20_1988_1993",
    "internal_id": 3001,
    "true_label": "教师反馈",
    "pred_label": "课堂沉寂",
    "true_idx": 6,
    "pred_idx": 9
  },
  {
    "sample_id": "T31_1328_1332",
    "internal_id": 314,
    "true_label": "教师提问",
    "pred_label": "学生发言",
    "true_idx": 0,
    "pred_idx": 1
  },
  {
    "sample_id": "T02_1336_1339",
    "internal_id": 1573,
    "true_label": "教师讲授",
    "pred_label": "课堂沉寂",
    "true_idx": 2,
    "pred_idx": 9
  },
  {
    "sample_id": "T11_0882_0886",
    "internal_id": 1915,
    "true_label": "学生发言",
    "pred_label": "课堂沉寂",
    "true_idx": 1,
    "pred_idx": 9
  },
  {
    "sample_id": "T31_0835_0840",
    "internal_id": 565,
    "true_label": "教师巡视",
    "pred_label": "课堂沉寂",
    "true_idx": 3,
    "pred_idx": 9
  },
  {
    "sample_id": "T18_1682_1686",
    "internal_id": 1182,
    "true_label": "教师讲授",
    "pred_label": "教师板书",
    "true_idx": 2,
    "pred_idx": 5
  },
  {
    "sample_id": "T19_2384_2390",
    "internal_id": 1696,
    "true_label": "学生发言",
    "pred_label": "课堂沉寂",
    "true_idx": 1,
    "pred_idx": 9
  },
  {
    "sample_id": "T03_0620_0623",
    "internal_id": 2495,
    "true_label": "学生发言",
    "pred_label": "课堂沉寂",
    "true_idx": 1,
    "pred_idx": 9
  },
  {
    "sample_id": "T13_0155_0159",
    "internal_id": 119,
    "true_label": "教师板书",
    "pred_label": "课堂沉寂",
    "true_idx": 5,
    "pred_idx": 9
  },
  {
    "sample_id": "T02_0787_0793",
    "internal_id": 1648,
    "true_label": "教师巡视",
    "pred_label": "课堂沉寂",
    "true_idx": 3,
    "pred_idx": 9
  },
  {
    "sample_id": "T12_1844_1849",
    "internal_id": 3982,
    "true_label": "教师板书",
    "pred_label": "教师巡视",
    "true_idx": 5,
    "pred_idx": 3
  },
  {
    "sample_id": "T01_0086_0089",
    "internal_id": 3341,
    "true_label": "教师提问",
    "pred_label": "教师指令",
    "true_idx": 0,
    "pred_idx": 4
  },
  {
    "sample_id": "T32_0214_0217",
    "internal_id": 848,
    "true_label": "教师讲授",
    "pred_label": "学生发言",
    "true_idx": 2,
    "pred_idx": 1
  },
  {
    "sample_id": "T19_2487_2492",
    "internal_id": 2272,
    "true_label": "教师讲授",
    "pred_label": "学生发言",
    "true_idx": 2,
    "pred_idx": 1
  },
  {
    "sample_id": "T01_1602_1606",
    "internal_id": 4108,
    "true_label": "教师讲授",
    "pred_label": "课堂沉寂",
    "true_idx": 2,
    "pred_idx": 9
  },
  {
    "sample_id": "T19_2348_2351",
    "internal_id": 412,
    "true_label": "学生发言",
    "pred_label": "课堂沉寂",
    "true_idx": 1,
    "pred_idx": 9
  },
  {
    "sample_id": "T21_2096_2101",
    "internal_id": 3284,
    "true_label": "教师反馈",
    "pred_label": "教师指令",
    "true_idx": 6,
    "pred_idx": 4
  },
  {
    "sample_id": "T30_1153_1157",
    "internal_id": 2969,
    "true_label": "教师反馈",
    "pred_label": "教师讲授",
    "true_idx": 6,
    "pred_idx": 2
  },
  {
    "sample_id": "T20_2438_2442",
    "internal_id": 3206,
    "true_label": "教师反馈",
    "pred_label": "教师板书",
    "true_idx": 6,
    "pred_idx": 5
  },
  {
    "sample_id": "T19_1867_1870",
    "internal_id": 3342,
    "true_label": "学生发言",
    "pred_label": "课堂沉寂",
    "true_idx": 1,
    "pred_idx": 9
  },
  {
    "sample_id": "T32_0008_0012",
    "internal_id": 3105,
    "true_label": "教师讲授",
    "pred_label": "教师巡视",
    "true_idx": 2,
    "pred_idx": 3
  },
  {
    "sample_id": "T14_0305_0309",
    "internal_id": 395,
    "true_label": "教师反馈",
    "pred_label": "教师讲授",
    "true_idx": 6,
    "pred_idx": 2
  },
  {
    "sample_id": "T30_1739_1743",
    "internal_id": 1258,
    "true_label": "教师反馈",
    "pred_label": "教师讲授",
    "true_idx": 6,
    "pred_idx": 2
  },
  {
    "sample_id": "T14_0211_0214",
    "internal_id": 4368,
    "true_label": "教师板书",
    "pred_label": "课堂沉寂",
    "true_idx": 5,
    "pred_idx": 9
  },
  {
    "sample_id": "T06_0942_0948",
    "internal_id": 560,
    "true_label": "教师反馈",
    "pred_label": "学生发言",
    "true_idx": 6,
    "pred_idx": 1
  },
  {
    "sample_id": "T03_2172_2175",
    "internal_id": 2191,
    "true_label": "教师巡视",
    "pred_label": "教师板书",
    "true_idx": 3,
    "pred_idx": 5
  },
  {
    "sample_id": "T33_1054_1058",
    "internal_id": 438,
    "true_label": "教师指令",
    "pred_label": "学生发言",
    "true_idx": 4,
    "pred_idx": 1
  },
  {
    "sample_id": "T03_2438_2442",
    "internal_id": 2441,
    "true_label": "教师指令",
    "pred_label": "教师讲授",
    "true_idx": 4,
    "pred_idx": 2
  },
  {
    "sample_id": "T07_1229_1235",
    "internal_id": 673,
    "true_label": "教师指令",
    "pred_label": "教师讲授",
    "true_idx": 4,
    "pred_idx": 2
  },
  {
    "sample_id": "T17_0247_0250",
    "internal_id": 3571,
    "true_label": "教师巡视",
    "pred_label": "教师讲授",
    "true_idx": 3,
    "pred_idx": 2
  },
  {
    "sample_id": "T15_0192_0196",
    "internal_id": 2394,
    "true_label": "课堂沉寂",
    "pred_label": "学生发言",
    "true_idx": 9,
    "pred_idx": 1
  },
  {
    "sample_id": "T21_1931_1936",
    "internal_id": 2253,
    "true_label": "技术操作",
    "pred_label": "教师板书",
    "true_idx": 7,
    "pred_idx": 5
  },
  {
    "sample_id": "T32_1994_1997",
    "internal_id": 4244,
    "true_label": "教师巡视",
    "pred_label": "学生发言",
    "true_idx": 3,
    "pred_idx": 1
  },
  {
    "sample_id": "T01_1734_1738",
    "internal_id": 3340,
    "true_label": "教师巡视",
    "pred_label": "课堂沉寂",
    "true_idx": 3,
    "pred_idx": 9
  },
  {
    "sample_id": "T05_0704_0707",
    "internal_id": 2291,
    "true_label": "教师巡视",
    "pred_label": "课堂沉寂",
    "true_idx": 3,
    "pred_idx": 9
  },
  {
    "sample_id": "T13_0800_0805",
    "internal_id": 3725,
    "true_label": "教师巡视",
    "pred_label": "课堂沉寂",
    "true_idx": 3,
    "pred_idx": 9
  },
  {
    "sample_id": "T03_2134_2139",
    "internal_id": 88,
    "true_label": "教师巡视",
    "pred_label": "课堂沉寂",
    "true_idx": 3,
    "pred_idx": 9
  },
  {
    "sample_id": "T21_1448_1453",
    "internal_id": 2593,
    "true_label": "教师巡视",
    "pred_label": "课堂沉寂",
    "true_idx": 3,
    "pred_idx": 9
  },
  {
    "sample_id": "T17_1314_1317",
    "internal_id": 2357,
    "true_label": "教师巡视",
    "pred_label": "课堂沉寂",
    "true_idx": 3,
    "pred_idx": 9
  },
  {
    "sample_id": "T03_2212_2217",
    "internal_id": 772,
    "true_label": "教师巡视",
    "pred_label": "课堂沉寂",
    "true_idx": 3,
    "pred_idx": 9
  },
  {
    "sample_id": "T18_1424_1427",
    "internal_id": 2287,
    "true_label": "教师巡视",
    "pred_label": "课堂沉寂",
    "true_idx": 3,
    "pred_idx": 9
  },
  {
    "sample_id": "T17_2315_2321",
    "internal_id": 2249,
    "true_label": "教师巡视",
    "pred_label": "教师板书",
    "true_idx": 3,
    "pred_idx": 5
  },
  {
    "sample_id": "T13_1331_1334",
    "internal_id": 1139,
    "true_label": "教师巡视",
    "pred_label": "课堂沉寂",
    "true_idx": 3,
    "pred_idx": 9
  },
  {
    "sample_id": "T32_1339_1342",
    "internal_id": 2784,
    "true_label": "教师巡视",
    "pred_label": "课堂沉寂",
    "true_idx": 3,
    "pred_idx": 9
  },
  {
    "sample_id": "T17_1351_1356",
    "internal_id": 3244,
    "true_label": "教师巡视",
    "pred_label": "课堂沉寂",
    "true_idx": 3,
    "pred_idx": 9
  },
  {
    "sample_id": "T32_0258_0261",
    "internal_id": 1416,
    "true_label": "教师讲授",
    "pred_label": "教师指令",
    "true_idx": 2,
    "pred_idx": 4
  },
  {
    "sample_id": "T04_2107_2112",
    "internal_id": 2480,
    "true_label": "教师板书",
    "pred_label": "课堂沉寂",
    "true_idx": 5,
    "pred_idx": 9
  },
  {
    "sample_id": "T18_0072_0077",
    "internal_id": 414,
    "true_label": "教师巡视",
    "pred_label": "课堂沉寂",
    "true_idx": 3,
    "pred_idx": 9
  },
  {
    "sample_id": "T21_0624_0628",
    "internal_id": 3225,
    "true_label": "教师巡视",
    "pred_label": "教师板书",
    "true_idx": 3,
    "pred_idx": 5
  },
  {
    "sample_id": "T21_0617_0620",
    "internal_id": 3912,
    "true_label": "教师巡视",
    "pred_label": "教师板书",
    "true_idx": 3,
    "pred_idx": 5
  },
  {
    "sample_id": "T01_1939_1943",
    "internal_id": 323,
    "true_label": "教师巡视",
    "pred_label": "课堂沉寂",
    "true_idx": 3,
    "pred_idx": 9
  },
  {
    "sample_id": "T03_2256_2261",
    "internal_id": 1261,
    "true_label": "教师巡视",
    "pred_label": "课堂沉寂",
    "true_idx": 3,
    "pred_idx": 9
  },
  {
    "sample_id": "T30_1512_1517",
    "internal_id": 1480,
    "true_label": "教师巡视",
    "pred_label": "课堂沉寂",
    "true_idx": 3,
    "pred_idx": 9
  },
  {
    "sample_id": "T12_0743_0748",
    "internal_id": 1288,
    "true_label": "教师讲授",
    "pred_label": "技术操作",
    "true_idx": 2,
    "pred_idx": 7
  },
  {
    "sample_id": "T03_1263_1267",
    "internal_id": 4132,
    "true_label": "教师巡视",
    "pred_label": "课堂沉寂",
    "true_idx": 3,
    "pred_idx": 9
  },
  {
    "sample_id": "T04_0690_0695",
    "internal_id": 758,
    "true_label": "教师讲授",
    "pred_label": "教师反馈",
    "true_idx": 2,
    "pred_idx": 6
  },
  {
    "sample_id": "T18_0551_0555",
    "internal_id": 2003,
    "true_label": "教师巡视",
    "pred_label": "课堂沉寂",
    "true_idx": 3,
    "pred_idx": 9
  },
  {
    "sample_id": "T30_0537_0542",
    "internal_id": 3696,
    "true_label": "学生发言",
    "pred_label": "教师讲授",
    "true_idx": 1,
    "pred_idx": 2
  },
  {
    "sample_id": "T17_1328_1333",
    "internal_id": 3618,
    "true_label": "教师巡视",
    "pred_label": "课堂沉寂",
    "true_idx": 3,
    "pred_idx": 9
  },
  {
    "sample_id": "T13_0583_0587",
    "internal_id": 970,
    "true_label": "教师巡视",
    "pred_label": "课堂沉寂",
    "true_idx": 3,
    "pred_idx": 9
  },
  {
    "sample_id": "T17_2242_2246",
    "internal_id": 2661,
    "true_label": "教师巡视",
    "pred_label": "课堂沉寂",
    "true_idx": 3,
    "pred_idx": 9
  },
  {
    "sample_id": "T06_0492_0495",
    "internal_id": 3319,
    "true_label": "教师巡视",
    "pred_label": "课堂沉寂",
    "true_idx": 3,
    "pred_idx": 9
  },
  {
    "sample_id": "T32_1749_1752",
    "internal_id": 3285,
    "true_label": "教师巡视",
    "pred_label": "课堂沉寂",
    "true_idx": 3,
    "pred_idx": 9
  },
  {
    "sample_id": "T01_2163_2168",
    "internal_id": 1575,
    "true_label": "教师讲授",
    "pred_label": "教师指令",
    "true_idx": 2,
    "pred_idx": 4
  },
  {
    "sample_id": "T18_1437_1440",
    "internal_id": 219,
    "true_label": "教师巡视",
    "pred_label": "课堂沉寂",
    "true_idx": 3,
    "pred_idx": 9
  },
  {
    "sample_id": "T05_0662_0665",
    "internal_id": 2263,
    "true_label": "教师巡视",
    "pred_label": "课堂沉寂",
    "true_idx": 3,
    "pred_idx": 9
  },
  {
    "sample_id": "T14_0003_0007",
    "internal_id": 2406,
    "true_label": "教师反馈",
    "pred_label": "课堂沉寂",
    "true_idx": 6,
    "pred_idx": 9
  },
  {
    "sample_id": "T09_1392_1396",
    "internal_id": 4038,
    "true_label": "教师指令",
    "pred_label": "课堂沉寂",
    "true_idx": 4,
    "pred_idx": 9
  },
  {
    "sample_id": "T05_0700_0704",
    "internal_id": 2680,
    "true_label": "教师巡视",
    "pred_label": "教师板书",
    "true_idx": 3,
    "pred_idx": 5
  },
  {
    "sample_id": "T20_1382_1387",
    "internal_id": 1610,
    "true_label": "教师板书",
    "pred_label": "教师巡视",
    "true_idx": 5,
    "pred_idx": 3
  },
  {
    "sample_id": "T30_0063_0067",
    "internal_id": 2896,
    "true_label": "教师讲授",
    "pred_label": "课堂沉寂",
    "true_idx": 2,
    "pred_idx": 9
  },
  {
    "sample_id": "T31_1305_1308",
    "internal_id": 2726,
    "true_label": "学生讨论",
    "pred_label": "课堂沉寂",
    "true_idx": 8,
    "pred_idx": 9
  },
  {
    "sample_id": "T33_0277_0283",
    "internal_id": 3471,
    "true_label": "教师提问",
    "pred_label": "教师巡视",
    "true_idx": 0,
    "pred_idx": 3
  },
  {
    "sample_id": "T02_0237_0241",
    "internal_id": 3442,
    "true_label": "教师讲授",
    "pred_label": "课堂沉寂",
    "true_idx": 2,
    "pred_idx": 9
  },
  {
    "sample_id": "T12_0367_0372",
    "internal_id": 3204,
    "true_label": "教师巡视",
    "pred_label": "课堂沉寂",
    "true_idx": 3,
    "pred_idx": 9
  },
  {
    "sample_id": "T16_1964_1969",
    "internal_id": 413,
    "true_label": "教师板书",
    "pred_label": "教师巡视",
    "true_idx": 5,
    "pred_idx": 3
  },
  {
    "sample_id": "T30_0480_0485",
    "internal_id": 143,
    "true_label": "教师讲授",
    "pred_label": "学生发言",
    "true_idx": 2,
    "pred_idx": 1
  },
  {
    "sample_id": "T05_1030_1033",
    "internal_id": 47,
    "true_label": "教师巡视",
    "pred_label": "课堂沉寂",
    "true_idx": 3,
    "pred_idx": 9
  },
  {
    "sample_id": "T01_1835_1840",
    "internal_id": 1677,
    "true_label": "课堂沉寂",
    "pred_label": "教师巡视",
    "true_idx": 9,
    "pred_idx": 3
  },
  {
    "sample_id": "T16_2468_2473",
    "internal_id": 2040,
    "true_label": "教师讲授",
    "pred_label": "学生发言",
    "true_idx": 2,
    "pred_idx": 1
  },
  {
    "sample_id": "T30_2423_2427",
    "internal_id": 3445,
    "true_label": "教师反馈",
    "pred_label": "教师巡视",
    "true_idx": 6,
    "pred_idx": 3
  },
  {
    "sample_id": "T31_0848_0852",
    "internal_id": 4260,
    "true_label": "教师巡视",
    "pred_label": "课堂沉寂",
    "true_idx": 3,
    "pred_idx": 9
  },
  {
    "sample_id": "T08_1514_1518",
    "internal_id": 3678,
    "true_label": "教师指令",
    "pred_label": "教师讲授",
    "true_idx": 4,
    "pred_idx": 2
  },
  {
    "sample_id": "T13_1454_1457",
    "internal_id": 4159,
    "true_label": "教师板书",
    "pred_label": "教师巡视",
    "true_idx": 5,
    "pred_idx": 3
  },
  {
    "sample_id": "T14_1357_1360",
    "internal_id": 3386,
    "true_label": "教师反馈",
    "pred_label": "学生发言",
    "true_idx": 6,
    "pred_idx": 1
  },
  {
    "sample_id": "T01_1071_1076",
    "internal_id": 3207,
    "true_label": "教师讲授",
    "pred_label": "学生发言",
    "true_idx": 2,
    "pred_idx": 1
  },
  {
    "sample_id": "T12_0532_0537",
    "internal_id": 2269,
    "true_label": "教师巡视",
    "pred_label": "课堂沉寂",
    "true_idx": 3,
    "pred_idx": 9
  },
  {
    "sample_id": "T18_0081_0086",
    "internal_id": 2878,
    "true_label": "教师巡视",
    "pred_label": "课堂沉寂",
    "true_idx": 3,
    "pred_idx": 9
  },
  {
    "sample_id": "T05_0707_0711",
    "internal_id": 2610,
    "true_label": "教师巡视",
    "pred_label": "课堂沉寂",
    "true_idx": 3,
    "pred_idx": 9
  },
  {
    "sample_id": "T30_1415_1418",
    "internal_id": 2816,
    "true_label": "教师反馈",
    "pred_label": "教师讲授",
    "true_idx": 6,
    "pred_idx": 2
  },
  {
    "sample_id": "T16_1605_1609",
    "internal_id": 2105,
    "true_label": "教师板书",
    "pred_label": "教师讲授",
    "true_idx": 5,
    "pred_idx": 2
  },
  {
    "sample_id": "T19_2445_2449",
    "internal_id": 1892,
    "true_label": "教师反馈",
    "pred_label": "学生发言",
    "true_idx": 6,
    "pred_idx": 1
  },
  {
    "sample_id": "T09_1453_1457",
    "internal_id": 1211,
    "true_label": "教师指令",
    "pred_label": "教师讲授",
    "true_idx": 4,
    "pred_idx": 2
  },
  {
    "sample_id": "T04_1722_1726",
    "internal_id": 2136,
    "true_label": "教师巡视",
    "pred_label": "课堂沉寂",
    "true_idx": 3,
    "pred_idx": 9
  },
  {
    "sample_id": "T16_1491_1496",
    "internal_id": 2647,
    "true_label": "教师讲授",
    "pred_label": "学生发言",
    "true_idx": 2,
    "pred_idx": 1
  },
  {
    "sample_id": "T19_0360_0363",
    "internal_id": 659,
    "true_label": "教师巡视",
    "pred_label": "课堂沉寂",
    "true_idx": 3,
    "pred_idx": 9
  },
  {
    "sample_id": "T32_1436_1440",
    "internal_id": 1291,
    "true_label": "教师提问",
    "pred_label": "学生发言",
    "true_idx": 0,
    "pred_idx": 1
  },
  {
    "sample_id": "T17_0098_0101",
    "internal_id": 1041,
    "true_label": "教师板书",
    "pred_label": "学生发言",
    "true_idx": 5,
    "pred_idx": 1
  },
  {
    "sample_id": "T31_1308_1311",
    "internal_id": 3177,
    "true_label": "教师指令",
    "pred_label": "学生发言",
    "true_idx": 4,
    "pred_idx": 1
  },
  {
    "sample_id": "T30_0156_0162",
    "internal_id": 2988,
    "true_label": "教师指令",
    "pred_label": "教师讲授",
    "true_idx": 4,
    "pred_idx": 2
  },
  {
    "sample_id": "T04_0193_0198",
    "internal_id": 2104,
    "true_label": "教师指令",
    "pred_label": "教师讲授",
    "true_idx": 4,
    "pred_idx": 2
  },
  {
    "sample_id": "T31_0405_0409",
    "internal_id": 2700,
    "true_label": "教师讲授",
    "pred_label": "学生发言",
    "true_idx": 2,
    "pred_idx": 1
  },
  {
    "sample_id": "T01_2046_2050",
    "internal_id": 1794,
    "true_label": "教师讲授",
    "pred_label": "学生发言",
    "true_idx": 2,
    "pred_idx": 1
  },
  {
    "sample_id": "T21_1444_1448",
    "internal_id": 3224,
    "true_label": "教师巡视",
    "pred_label": "课堂沉寂",
    "true_idx": 3,
    "pred_idx": 9
  },
  {
    "sample_id": "T11_0905_0910",
    "internal_id": 3119,
    "true_label": "教师讲授",
    "pred_label": "教师板书",
    "true_idx": 2,
    "pred_idx": 5
  },
  {
    "sample_id": "T12_1787_1792",
    "internal_id": 2464,
    "true_label": "教师指令",
    "pred_label": "教师讲授",
    "true_idx": 4,
    "pred_idx": 2
  },
  {
    "sample_id": "T16_0263_0267",
    "internal_id": 2472,
    "true_label": "教师巡视",
    "pred_label": "教师提问",
    "true_idx": 3,
    "pred_idx": 0
  },
  {
    "sample_id": "T18_1427_1430",
    "internal_id": 376,
    "true_label": "教师巡视",
    "pred_label": "课堂沉寂",
    "true_idx": 3,
    "pred_idx": 9
  },
  {
    "sample_id": "T12_1668_1674",
    "internal_id": 4389,
    "true_label": "教师巡视",
    "pred_label": "教师板书",
    "true_idx": 3,
    "pred_idx": 5
  },
  {
    "sample_id": "T32_1011_1016",
    "internal_id": 3794,
    "true_label": "教师巡视",
    "pred_label": "教师板书",
    "true_idx": 3,
    "pred_idx": 5
  },
  {
    "sample_id": "T04_2306_2310",
    "internal_id": 2468,
    "true_label": "技术操作",
    "pred_label": "教师讲授",
    "true_idx": 7,
    "pred_idx": 2
  },
  {
    "sample_id": "T32_0973_0978",
    "internal_id": 628,
    "true_label": "教师巡视",
    "pred_label": "课堂沉寂",
    "true_idx": 3,
    "pred_idx": 9
  },
  {
    "sample_id": "T16_1628_1631",
    "internal_id": 2065,
    "true_label": "教师板书",
    "pred_label": "学生发言",
    "true_idx": 5,
    "pred_idx": 1
  },
  {
    "sample_id": "T17_0616_0619",
    "internal_id": 1205,
    "true_label": "技术操作",
    "pred_label": "教师板书",
    "true_idx": 7,
    "pred_idx": 5
  },
  {
    "sample_id": "T17_2294_2299",
    "internal_id": 4028,
    "true_label": "教师巡视",
    "pred_label": "课堂沉寂",
    "true_idx": 3,
    "pred_idx": 9
  },
  {
    "sample_id": "T03_1232_1235",
    "internal_id": 984,
    "true_label": "教师巡视",
    "pred_label": "教师板书",
    "true_idx": 3,
    "pred_idx": 5
  },
  {
    "sample_id": "T10_1118_1122",
    "internal_id": 620,
    "true_label": "教师巡视",
    "pred_label": "教师板书",
    "true_idx": 3,
    "pred_idx": 5
  },
  {
    "sample_id": "T13_0301_0303",
    "internal_id": 288,
    "true_label": "学生发言",
    "pred_label": "教师提问",
    "true_idx": 1,
    "pred_idx": 0
  },
  {
    "sample_id": "T05_0540_0544",
    "internal_id": 4250,
    "true_label": "教师巡视",
    "pred_label": "课堂沉寂",
    "true_idx": 3,
    "pred_idx": 9
  },
  {
    "sample_id": "T20_1802_1805",
    "internal_id": 2581,
    "true_label": "教师巡视",
    "pred_label": "教师板书",
    "true_idx": 3,
    "pred_idx": 5
  },
  {
    "sample_id": "T04_1683_1686",
    "internal_id": 558,
    "true_label": "教师巡视",
    "pred_label": "课堂沉寂",
    "true_idx": 3,
    "pred_idx": 9
  },
  {
    "sample_id": "T11_0673_0677",
    "internal_id": 396,
    "true_label": "教师板书",
    "pred_label": "课堂沉寂",
    "true_idx": 5,
    "pred_idx": 9
  },
  {
    "sample_id": "T32_0255_0258",
    "internal_id": 2254,
    "true_label": "教师讲授",
    "pred_label": "学生发言",
    "true_idx": 2,
    "pred_idx": 1
  },
  {
    "sample_id": "T06_0068_0072",
    "internal_id": 3290,
    "true_label": "教师讲授",
    "pred_label": "教师指令",
    "true_idx": 2,
    "pred_idx": 4
  },
  {
    "sample_id": "T02_0513_0517",
    "internal_id": 58,
    "true_label": "教师讲授",
    "pred_label": "教师板书",
    "true_idx": 2,
    "pred_idx": 5
  },
  {
    "sample_id": "T32_1335_1339",
    "internal_id": 4085,
    "true_label": "教师巡视",
    "pred_label": "课堂沉寂",
    "true_idx": 3,
    "pred_idx": 9
  },
  {
    "sample_id": "T01_1411_1415",
    "internal_id": 1512,
    "true_label": "教师板书",
    "pred_label": "教师巡视",
    "true_idx": 5,
    "pred_idx": 3
  },
  {
    "sample_id": "T20_0778_0783",
    "internal_id": 920,
    "true_label": "教师板书",
    "pred_label": "教师巡视",
    "true_idx": 5,
    "pred_idx": 3
  },
  {
    "sample_id": "T07_2133_2137",
    "internal_id": 145,
    "true_label": "教师提问",
    "pred_label": "学生发言",
    "true_idx": 0,
    "pred_idx": 1
  }
]